Workbook

Sheet DASHBOARD
B2: ⚓ MARITIME CHOKEPOINT RISK MONITOR | K2: LAST UPDATED:
B3: Three-Ring Model · Six-Pillar Country Risk · 18 Global Chokepoints | K3: 5 July 2026, 19:04 Danish Summer Time (CEST)
B5: ▼ SELECT CHOKEPOINT | C5: Bab el-Mandeb | I5: FINAL SCORE | J5: =IFERROR(VLOOKUP($C$5,RING_ENGINE!$A$4:$K$21,9,FALSE()),"—") -> 61.975
B6: Change dropdown above | I6: BAND | J6: =IFERROR(VLOOKUP($C$5,RING_ENGINE!$A$4:$K$21,10,FALSE()),"—") -> HIGH
B8: ▼ CHOKEPOINT PROFILE
B9: PRIMARY | C9: =IFERROR(VLOOKUP($C$5,RING_ENGINE!$A$4:$K$21,2,FALSE()),"—") -> Yemen, Djibouti, Eritrea | F9: SURROUNDING | G9: =IFERROR(VLOOKUP($C$5,RING_ENGINE!$A$4:$K$21,3,FALSE()),"—") -> Saudi Arabia, Somalia, Ethiopia | I9: INFLUENCERS | J9: =IFERROR(VLOOKUP($C$5,RING_ENGINE!$A$4:$K$21,4,FALSE()),"—") -> United States, Iran, China, France, Saudi Arabia
B11: ▼ RING SCORES | Weighted contribution to Final
B12: Ring | C12: Countries | D12: Risk Score | E12: Weight | F12: Contribution | G12: Description
B13: Ring 1: Primary | C13: =IFERROR(VLOOKUP($C$5,RING_ENGINE!$A$4:$K$21,2,FALSE()),"—") -> Yemen, Djibouti, Eritrea | D13: =IFERROR(VLOOKUP($C$5,RING_ENGINE!$A$4:$K$21,5,FALSE),"—") -> 69.8 | E13: ='00_CONFIG'!C5 -> 0.5 | F13: =D13*E13 -> 34.9 | G13: Physical control of chokepoint
B14: Ring 2: Surrounding | C14: =IFERROR(VLOOKUP($C$5,RING_ENGINE!$A$4:$K$21,3,FALSE()),"—") -> Saudi Arabia, Somalia, Ethiopia | D14: =IFERROR(VLOOKUP($C$5,RING_ENGINE!$A$4:$K$21,6,FALSE),"—") -> 67.9 | E14: ='00_CONFIG'!C6 -> 0.25 | F14: =D14*E14 -> 16.975 | G14: Littoral neighbors
B15: Ring 3: Influencers | C15: =IFERROR(VLOOKUP($C$5,RING_ENGINE!$A$4:$K$21,4,FALSE()),"—") -> United States, Iran, China, France, Saudi Arabia | D15: =IFERROR(VLOOKUP($C$5,RING_ENGINE!$A$4:$K$21,7,FALSE),"—") -> 42 | E15: ='00_CONFIG'!C7 -> 0.15 | F15: =D15*E15 -> 6.3 | G15: Great-power geopolitical pressure
B16: Ring 4: Environment | C16: — | D16: =IFERROR(VLOOKUP($C$5,RING_ENGINE!$A$4:$K$21,8,FALSE),"—") -> 38 | E16: ='00_CONFIG'!C8 -> 0.1 | F16: =D16*E16 -> 3.8 | G16: Weather (ERA5) · geography · bypass (0-100 scaled)
B18: ▼ RECOMMENDED ACTION
B19: =IFERROR(IF(VLOOKUP($C$5,RING_ENGINE!$A$4:$K$21,10,FALSE())="LOW","Standard monitoring. Annual review.",IF(VLOOKUP($C$5,RING_ENGINE!$A$4:$K$21,10,FALSE())="MODERATE","Enhanced monitoring. Quarterly review. Identify bypass options.",IF(VLOOKUP($C$5,RING_ENGINE!$A$4:$K$21,10,FALSE())="ELEVATED","Flag for review. Map bypass routes. Monthly checks.",IF(VLOOKUP($C$5,RING_ENGINE!$A$4:$K$21,10,FALSE())="HIGH","Escalate to leadership. Activate contingency routing. Weekly review.","Immediate escalation. Do not rely on this route. Board approval required.")))),"—") -> Escalate to leadership. Activate contingency routing. Weekly review.
B21: ▼ ALL 18 CHOKEPOINTS — Ranked by Final Score
B22: # | C22: Chokepoint | D22: R1 | E22: R2 | F22: R3 | G22: Env | H22: SCORE | I22: BAND | J22: Bypass | K22: Notes
B23: 1 | C23: Bab el-Mandeb | D23: =IFERROR(VLOOKUP($C23,RING_ENGINE!$A$4:$K$21,5,FALSE),"—") -> 69.8 | E23: =IFERROR(VLOOKUP($C23,RING_ENGINE!$A$4:$K$21,6,FALSE),"—") -> 67.9 | F23: =IFERROR(VLOOKUP($C23,RING_ENGINE!$A$4:$K$21,7,FALSE),"—") -> 42 | G23: =IFERROR(VLOOKUP($C23,RING_ENGINE!$A$4:$K$21,8,FALSE),"—") -> 38 | H23: =IFERROR(VLOOKUP($C23,RING_ENGINE!$A$4:$K$21,9,FALSE),"—") -> 61.975 | I23: =IFERROR(VLOOKUP($C23,RING_ENGINE!$A$4:$K$21,10,FALSE),"—") -> HIGH | J23: =IFERROR(VLOOKUP($C23,RING_ENGINE!$A$4:$K$21,11,FALSE),"—") -> Cape of Good Hope | K23: =IFERROR(VLOOKUP($C23,CP_OVERVIEW!$B$4:$H$21,7,FALSE),"—") -> Active conflict zone. Houthi missile/drone threat since Oct 2023. Undersea cables, 25% of global data traffic between Asia and Europe.
B24: 2 | C24: Northern Sea Route | D24: =IFERROR(VLOOKUP($C24,RING_ENGINE!$A$4:$K$21,5,FALSE),"—") -> 66.6 | E24: =IFERROR(VLOOKUP($C24,RING_ENGINE!$A$4:$K$21,6,FALSE),"—") -> 18.1 | F24: =IFERROR(VLOOKUP($C24,RING_ENGINE!$A$4:$K$21,7,FALSE),"—") -> 28 | G24: =IFERROR(VLOOKUP($C24,RING_ENGINE!$A$4:$K$21,8,FALSE),"—") -> 36 | H24: =IFERROR(VLOOKUP($C24,RING_ENGINE!$A$4:$K$21,9,FALSE),"—") -> 45.625 | I24: =IFERROR(VLOOKUP($C24,RING_ENGINE!$A$4:$K$21,10,FALSE),"—") -> ELEVATED | J24: =IFERROR(VLOOKUP($C24,RING_ENGINE!$A$4:$K$21,11,FALSE),"—") -> Traditional Suez / Panama lanes | K24: =IFERROR(VLOOKUP($C24,CP_OVERVIEW!$B$4:$H$21,7,FALSE),"—") -> Ice-dependent. Russian icebreaker monopoly. China Arctic interest growing.
B25: 3 | C25: Bosphorus / Turkish Straits | D25: =IFERROR(VLOOKUP($C25,RING_ENGINE!$A$4:$K$21,5,FALSE),"—") -> 57.7 | E25: =IFERROR(VLOOKUP($C25,RING_ENGINE!$A$4:$K$21,6,FALSE),"—") -> 45.6 | F25: =IFERROR(VLOOKUP($C25,RING_ENGINE!$A$4:$K$21,7,FALSE),"—") -> 35.7 | G25: =IFERROR(VLOOKUP($C25,RING_ENGINE!$A$4:$K$21,8,FALSE),"—") -> 59 | H25: =IFERROR(VLOOKUP($C25,RING_ENGINE!$A$4:$K$21,9,FALSE),"—") -> 51.505 | I25: =IFERROR(VLOOKUP($C25,RING_ENGINE!$A$4:$K$21,10,FALSE),"—") -> ELEVATED | J25: =IFERROR(VLOOKUP($C25,RING_ENGINE!$A$4:$K$21,11,FALSE),"—") -> None (no bypass exists) | K25: =IFERROR(VLOOKUP($C25,CP_OVERVIEW!$B$4:$H$21,7,FALSE),"—") -> Russian Black Sea Fleet access via Turkey under 1936 Montreux Convention.
B26: 4 | C26: Cape of Good Hope | D26: =IFERROR(VLOOKUP($C26,RING_ENGINE!$A$4:$K$21,5,FALSE),"—") -> 48.2 | E26: =IFERROR(VLOOKUP($C26,RING_ENGINE!$A$4:$K$21,6,FALSE),"—") -> 56.8 | F26: =IFERROR(VLOOKUP($C26,RING_ENGINE!$A$4:$K$21,7,FALSE),"—") -> 38.9 | G26: =IFERROR(VLOOKUP($C26,RING_ENGINE!$A$4:$K$21,8,FALSE),"—") -> 18 | H26: =IFERROR(VLOOKUP($C26,RING_ENGINE!$A$4:$K$21,9,FALSE),"—") -> 45.935 | I26: =IFERROR(VLOOKUP($C26,RING_ENGINE!$A$4:$K$21,10,FALSE),"—") -> ELEVATED | J26: =IFERROR(VLOOKUP($C26,RING_ENGINE!$A$4:$K$21,11,FALSE),"—") -> Primary bypass route | K26: =IFERROR(VLOOKUP($C26,CP_OVERVIEW!$B$4:$H$21,7,FALSE),"—") -> Not a chokepoint per se — the bypass route. Risk = SA stability.
B27: 5 | C27: Suez Canal | D27: =IFERROR(VLOOKUP($C27,RING_ENGINE!$A$4:$K$21,5,FALSE),"—") -> 52.7 | E27: =IFERROR(VLOOKUP($C27,RING_ENGINE!$A$4:$K$21,6,FALSE),"—") -> 52.8 | F27: =IFERROR(VLOOKUP($C27,RING_ENGINE!$A$4:$K$21,7,FALSE),"—") -> 41.8 | G27: =IFERROR(VLOOKUP($C27,RING_ENGINE!$A$4:$K$21,8,FALSE),"—") -> 60 | H27: =IFERROR(VLOOKUP($C27,RING_ENGINE!$A$4:$K$21,9,FALSE),"—") -> 51.82 | I27: =IFERROR(VLOOKUP($C27,RING_ENGINE!$A$4:$K$21,10,FALSE),"—") -> ELEVATED | J27: =IFERROR(VLOOKUP($C27,RING_ENGINE!$A$4:$K$21,11,FALSE),"—") -> Cape of Good Hope | K27: =IFERROR(VLOOKUP($C27,CP_OVERVIEW!$B$4:$H$21,7,FALSE),"—") -> ~100 ships/day. Houthi threat diverting traffic to Cape.
B28: 6 | C28: Strait of Hormuz | D28: =IFERROR(VLOOKUP($C28,RING_ENGINE!$A$4:$K$21,5,FALSE),"—") -> 52 | E28: =IFERROR(VLOOKUP($C28,RING_ENGINE!$A$4:$K$21,6,FALSE),"—") -> 37.2 | F28: =IFERROR(VLOOKUP($C28,RING_ENGINE!$A$4:$K$21,7,FALSE),"—") -> 41.1 | G28: =IFERROR(VLOOKUP($C28,RING_ENGINE!$A$4:$K$21,8,FALSE),"—") -> 38 | H28: =IFERROR(VLOOKUP($C28,RING_ENGINE!$A$4:$K$21,9,FALSE),"—") -> 45.265 | I28: =IFERROR(VLOOKUP($C28,RING_ENGINE!$A$4:$K$21,10,FALSE),"—") -> ELEVATED | J28: =IFERROR(VLOOKUP($C28,RING_ENGINE!$A$4:$K$21,11,FALSE),"—") -> None (no bypass exists) | K28: =IFERROR(VLOOKUP($C28,CP_OVERVIEW!$B$4:$H$21,7,FALSE),"—") -> ~21 Mbbl/day oil transit. Iranian closure = immediate global oil shock.
B29: 7 | C29: Windward Passage | D29: =IFERROR(VLOOKUP($C29,RING_ENGINE!$A$4:$K$21,5,FALSE),"—") -> 52.4 | E29: =IFERROR(VLOOKUP($C29,RING_ENGINE!$A$4:$K$21,6,FALSE),"—") -> 35.3 | F29: =IFERROR(VLOOKUP($C29,RING_ENGINE!$A$4:$K$21,7,FALSE),"—") -> 38.5 | G29: =IFERROR(VLOOKUP($C29,RING_ENGINE!$A$4:$K$21,8,FALSE),"—") -> 25 | H29: =IFERROR(VLOOKUP($C29,RING_ENGINE!$A$4:$K$21,9,FALSE),"—") -> 43.3 | I29: =IFERROR(VLOOKUP($C29,RING_ENGINE!$A$4:$K$21,10,FALSE),"—") -> ELEVATED | J29: =IFERROR(VLOOKUP($C29,RING_ENGINE!$A$4:$K$21,11,FALSE),"—") -> Yucatan Channel | K29: =IFERROR(VLOOKUP($C29,CP_OVERVIEW!$B$4:$H$21,7,FALSE),"—") -> Haiti instability affects maritime security monitoring.
B30: 8 | C30: Florida Straits | D30: =IFERROR(VLOOKUP($C30,RING_ENGINE!$A$4:$K$21,5,FALSE),"—") -> 32.1 | E30: =IFERROR(VLOOKUP($C30,RING_ENGINE!$A$4:$K$21,6,FALSE),"—") -> 45.9 | F30: =IFERROR(VLOOKUP($C30,RING_ENGINE!$A$4:$K$21,7,FALSE),"—") -> 38.5 | G30: =IFERROR(VLOOKUP($C30,RING_ENGINE!$A$4:$K$21,8,FALSE),"—") -> 19 | H30: =IFERROR(VLOOKUP($C30,RING_ENGINE!$A$4:$K$21,9,FALSE),"—") -> 35.2 | I30: =IFERROR(VLOOKUP($C30,RING_ENGINE!$A$4:$K$21,10,FALSE),"—") -> MODERATE | J30: =IFERROR(VLOOKUP($C30,RING_ENGINE!$A$4:$K$21,11,FALSE),"—") -> Gulf of Mexico interior | K30: =IFERROR(VLOOKUP($C30,CP_OVERVIEW!$B$4:$H$21,7,FALSE),"—") -> Key Gulf of Mexico energy transit. Cuba–China cooperation concern.
B31: 9 | C31: Panama Canal | D31: =IFERROR(VLOOKUP($C31,RING_ENGINE!$A$4:$K$21,5,FALSE),"—") -> 35.6 | E31: =IFERROR(VLOOKUP($C31,RING_ENGINE!$A$4:$K$21,6,FALSE),"—") -> 38.1 | F31: =IFERROR(VLOOKUP($C31,RING_ENGINE!$A$4:$K$21,7,FALSE),"—") -> 38.5 | G31: =IFERROR(VLOOKUP($C31,RING_ENGINE!$A$4:$K$21,8,FALSE),"—") -> 52 | H31: =IFERROR(VLOOKUP($C31,RING_ENGINE!$A$4:$K$21,9,FALSE),"—") -> 38.3 | I31: =IFERROR(VLOOKUP($C31,RING_ENGINE!$A$4:$K$21,10,FALSE),"—") -> MODERATE | J31: =IFERROR(VLOOKUP($C31,RING_ENGINE!$A$4:$K$21,11,FALSE),"—") -> Cape Horn / Strait of Magellan | K31: =IFERROR(VLOOKUP($C31,CP_OVERVIEW!$B$4:$H$21,7,FALSE),"—") -> 2023-24 drought cut capacity 30%. China port influence growing.
B32: 10 | C32: Cape Horn | D32: =IFERROR(VLOOKUP($C32,RING_ENGINE!$A$4:$K$21,5,FALSE),"—") -> 31.9 | E32: =IFERROR(VLOOKUP($C32,RING_ENGINE!$A$4:$K$21,6,FALSE),"—") -> 32.3 | F32: =IFERROR(VLOOKUP($C32,RING_ENGINE!$A$4:$K$21,7,FALSE),"—") -> 32.6 | G32: =IFERROR(VLOOKUP($C32,RING_ENGINE!$A$4:$K$21,8,FALSE),"—") -> 28 | H32: =IFERROR(VLOOKUP($C32,RING_ENGINE!$A$4:$K$21,9,FALSE),"—") -> 31.715 | I32: =IFERROR(VLOOKUP($C32,RING_ENGINE!$A$4:$K$21,10,FALSE),"—") -> MODERATE | J32: =IFERROR(VLOOKUP($C32,RING_ENGINE!$A$4:$K$21,11,FALSE),"—") -> Strait of Magellan | K32: =IFERROR(VLOOKUP($C32,CP_OVERVIEW!$B$4:$H$21,7,FALSE),"—") -> Extreme weather. Last-resort route. Low control risk (open ocean).
B33: 11 | C33: Strait of Malacca | D33: =IFERROR(VLOOKUP($C33,RING_ENGINE!$A$4:$K$21,5,FALSE),"—") -> 31.3 | E33: =IFERROR(VLOOKUP($C33,RING_ENGINE!$A$4:$K$21,6,FALSE),"—") -> 40.3 | F33: =IFERROR(VLOOKUP($C33,RING_ENGINE!$A$4:$K$21,7,FALSE),"—") -> 31.5 | G33: =IFERROR(VLOOKUP($C33,RING_ENGINE!$A$4:$K$21,8,FALSE),"—") -> 36 | H33: =IFERROR(VLOOKUP($C33,RING_ENGINE!$A$4:$K$21,9,FALSE),"—") -> 34.05 | I33: =IFERROR(VLOOKUP($C33,RING_ENGINE!$A$4:$K$21,10,FALSE),"—") -> MODERATE | J33: =IFERROR(VLOOKUP($C33,RING_ENGINE!$A$4:$K$21,11,FALSE),"—") -> Lombok / Sunda Strait | K33: =IFERROR(VLOOKUP($C33,CP_OVERVIEW!$B$4:$H$21,7,FALSE),"—") -> Busiest chokepoint by vessel count. Piracy historically significant.
B34: 12 | C34: Korea Strait | D34: =IFERROR(VLOOKUP($C34,RING_ENGINE!$A$4:$K$21,5,FALSE),"—") -> 17.5 | E34: =IFERROR(VLOOKUP($C34,RING_ENGINE!$A$4:$K$21,6,FALSE),"—") -> 59.5 | F34: =IFERROR(VLOOKUP($C34,RING_ENGINE!$A$4:$K$21,7,FALSE),"—") -> 47.9 | G34: =IFERROR(VLOOKUP($C34,RING_ENGINE!$A$4:$K$21,8,FALSE),"—") -> 27 | H34: =IFERROR(VLOOKUP($C34,RING_ENGINE!$A$4:$K$21,9,FALSE),"—") -> 33.51 | I34: =IFERROR(VLOOKUP($C34,RING_ENGINE!$A$4:$K$21,10,FALSE),"—") -> MODERATE | J34: =IFERROR(VLOOKUP($C34,RING_ENGINE!$A$4:$K$21,11,FALSE),"—") -> Sea of Japan / Pacific | K34: =IFERROR(VLOOKUP($C34,CP_OVERVIEW!$B$4:$H$21,7,FALSE),"—") -> DPRK missile overflight risk. High US/JMSDF presence.
... B40: 18 | C40: Danish Straits | D40: =IFERROR(VLOOKUP($C40,RING_ENGINE!$A$4:$K$21,5,FALSE),"—") -> 9.3 | E40: =IFERROR(VLOOKUP($C40,RING_ENGINE!$A$4:$K$21,6,FALSE),"—") -> 26.2 | F40: =IFERROR(VLOOKUP($C40,RING_ENGINE!$A$4:$K$21,7,FALSE),"—") -> 35.7 | G40: =IFERROR(VLOOKUP($C40,RING_ENGINE!$A$4:$K$21,8,FALSE),"—") -> 53 | H40: =IFERROR(VLOOKUP($C40,RING_ENGINE!$A$4:$K$21,9,FALSE),"—") -> 21.855 | I40: =IFERROR(VLOOKUP($C40,RING_ENGINE!$A$4:$K$21,10,FALSE),"—") -> MODERATE | J40: =IFERROR(VLOOKUP($C40,RING_ENGINE!$A$4:$K$21,11,FALSE),"—") -> None (no bypass exists) | K40: =IFERROR(VLOOKUP($C40,CP_OVERVIEW!$B$4:$H$21,7,FALSE),"—") -> Russian Baltic Fleet passage. NATO Article 5 littoral states.
B42: Maritime Chokepoint Risk Monitor · WPR + FSI + ACLED + CIA Factbook

Sheet CP_OVERVIEW
A1: CP_OVERVIEW | Chokepoint Definitions · Three-Ring Country Assignments
A2: Ring 1 = physical controllers · Ring 2 = adjacent · Ring 3 = outside · Env = 0-10 hazard
A3: # | B3: Chokepoint | C3: Ring 1: Primary | D3: Ring 2: Surrounding | E3: Ring 3: Outside Influencers | F3: Env (0-10) | G3: Bypass Route | H3: Notes
A4: 1 | B4: Strait of Hormuz | C4: Iran, Oman | D4: United Arab Emirates, Saudi Arabia, Qatar, Bahrain, Kuwait, Iraq | E4: United States, China, Russia, United Kingdom | F4: 6 | G4: None | H4: ~21 Mbbl/day oil transit. Iranian closure = immediate global oil shock.
A5: 2 | B5: Strait of Malacca | C5: Malaysia, Indonesia, Singapore | D5: Thailand, Vietnam | E5: China, United States, Japan, India, Australia | F5: 5 | G5: Lombok / Sunda Strait | H5: Busiest chokepoint by vessel count. Piracy historically significant.
A6: 3 | B6: Suez Canal | C6: Egypt | D6: Israel, Saudi Arabia, Jordan, Libya | E6: United States, China, France, Russia | F6: 4 | G6: Cape of Good Hope | H6: ~100 ships/day. Houthi threat diverting traffic to Cape.
A7: 4 | B7: Bab el-Mandeb | C7: Yemen, Djibouti, Eritrea | D7: Saudi Arabia, Somalia, Ethiopia | E7: United States, Iran, China, France, Saudi Arabia | F7: 8 | G7: Cape of Good Hope | H7: Active conflict zone. Houthi missile/drone threat since Oct 2023. Undersea cables, 25% of global data traffic between Asia and Europe.
A8: 5 | B8: Panama Canal | C8: Panama | D8: Colombia, Costa Rica, United States | E8: United States, China | F8: 3 | G8: Cape Horn / Strait of Magellan | H8: 2023-24 drought cut capacity 30%. China port influence growing.
A9: 6 | B9: Bosphorus / Turkish Straits | C9: Turkey | D9: Bulgaria, Romania, Ukraine, Russia, Georgia | E9: United States, Russia, France, United Kingdom | F9: 5 | G9: None | H9: Russian Black Sea Fleet access via Turkey under 1936 Montreux Convention.
A10: 7 | B10: Strait of Gibraltar | C10: Spain, Morocco, United Kingdom | D10: Portugal, Algeria | E10: United States, France, Morocco | F10: 3 | G10: Atlantic open ocean | H10: NATO-monitored. Gibraltar sovereignty periodically contested.
A11: 8 | B11: Cape of Good Hope | C11: South Africa | D11: Namibia, Mozambique, Madagascar | E11: China, United States, France, India | F11: 6 | G11: Primary bypass route | H11: Not a chokepoint per se — the bypass route. Risk = SA stability.
A12: 9 | B12: Danish Straits | C12: Denmark, Sweden | D12: Germany, Poland, Norway, Finland, Russia | E12: United States, Russia, United Kingdom, France | F12: 4 | G12: None | H12: Russian Baltic Fleet passage. NATO Article 5 littoral states.
A13: 10 | B13: Taiwan Strait | C13: Taiwan, China | D13: Philippines, Japan | E13: United States, Japan, Australia, South Korea, India | F13: 4 | G13: Philippine Sea (east of Taiwan) | H13: Military flashpoint. ~50% global semiconductor supply chain at stake.
A14: 11 | B14: Korea Strait | C14: South Korea, Japan | D14: North Korea | E14: United States, China, Russia | F14: 4 | G14: Sea of Japan / Pacific | H14: DPRK missile overflight risk. High US/JMSDF presence.
A15: 12 | B15: Lombok Strait | C15: Indonesia | D15: Australia | E15: China, United States, Japan, Australia | F15: 3 | G15: Malacca Strait | H15: Primary deep-water Malacca bypass for tankers/carriers.
... A21: 18 | B21: Northern Sea Route | C21: Russia | D21: Norway, Canada, United States | E21: China, France, Japan | F21: 9 | G21: Traditional Suez / Panama lanes | H21: Ice-dependent. Russian icebreaker monopoly. China Arctic interest growing.

Sheet RING_ENGINE
A1: RING_ENGINE | Averages COUNTRY_RISK per Ring · Weighted Final Score
A2: R1/R2/R3 scores = mean of Country Risk Scores in that ring · Final = R1×50% + R2×25% + R3×15% + Env×10%
A3: Chokepoint | B3: Ring 1 Countries | C3: Ring 2 Countries | D3: Ring 3 Countries | E3: R1 Score | F3: R2 Score | G3: R3 Score | H3: Env×10 | I3: FINAL | J3: BAND | K3: Bypass
A4: Strait of Hormuz | B4: Iran, Oman | C4: United Arab Emirates, Saudi Arabia, Qatar, Bahrain, Kuwait, Iraq | D4: United States, China, Russia, United Kingdom | E4: 52 | F4: 37.2 | G4: 41.1 | H4: 38 | I4: =E4*'00_CONFIG'!$C$5+F4*'00_CONFIG'!$C$6+G4*'00_CONFIG'!$C$7+H4*'00_CONFIG'!$C$8 -> 45.265 | J4: =IF(I4<=20,"LOW",IF(I4<=40,"MODERATE",IF(I4<=60,"ELEVATED",IF(I4<=80,"HIGH","CRITICAL")))) -> ELEVATED | K4: None (no bypass exists)
A5: Strait of Malacca | B5: Malaysia, Indonesia, Singapore | C5: Thailand, Vietnam | D5: China, United States, Japan, India, Australia | E5: 31.3 | F5: 40.3 | G5: 31.5 | H5: 36 | I5: =E5*'00_CONFIG'!$C$5+F5*'00_CONFIG'!$C$6+G5*'00_CONFIG'!$C$7+H5*'00_CONFIG'!$C$8 -> 34.05 | J5: =IF(I5<=20,"LOW",IF(I5<=40,"MODERATE",IF(I5<=60,"ELEVATED",IF(I5<=80,"HIGH","CRITICAL")))) -> MODERATE | K5: Lombok / Sunda Strait
A6: Suez Canal | B6: Egypt | C6: Israel, Saudi Arabia, Jordan, Libya | D6: United States, China, France, Russia | E6: 52.7 | F6: 52.8 | G6: 41.8 | H6: 60 | I6: =E6*'00_CONFIG'!$C$5+F6*'00_CONFIG'!$C$6+G6*'00_CONFIG'!$C$7+H6*'00_CONFIG'!$C$8 -> 51.82 | J6: =IF(I6<=20,"LOW",IF(I6<=40,"MODERATE",IF(I6<=60,"ELEVATED",IF(I6<=80,"HIGH","CRITICAL")))) -> ELEVATED | K6: Cape of Good Hope
A7: Bab el-Mandeb | B7: Yemen, Djibouti, Eritrea | C7: Saudi Arabia, Somalia, Ethiopia | D7: United States, Iran, China, France, Saudi Arabia | E7: 69.8 | F7: 67.9 | G7: 42 | H7: 38 | I7: =E7*'00_CONFIG'!$C$5+F7*'00_CONFIG'!$C$6+G7*'00_CONFIG'!$C$7+H7*'00_CONFIG'!$C$8 -> 61.975 | J7: =IF(I7<=20,"LOW",IF(I7<=40,"MODERATE",IF(I7<=60,"ELEVATED",IF(I7<=80,"HIGH","CRITICAL")))) -> HIGH | K7: Cape of Good Hope
A8: Panama Canal | B8: Panama | C8: Colombia, Costa Rica, United States | D8: United States, China | E8: 35.6 | F8: 38.1 | G8: 38.5 | H8: 52 | I8: =E8*'00_CONFIG'!$C$5+F8*'00_CONFIG'!$C$6+G8*'00_CONFIG'!$C$7+H8*'00_CONFIG'!$C$8 -> 38.3 | J8: =IF(I8<=20,"LOW",IF(I8<=40,"MODERATE",IF(I8<=60,"ELEVATED",IF(I8<=80,"HIGH","CRITICAL")))) -> MODERATE | K8: Cape Horn / Strait of Magellan
A9: Bosphorus / Turkish Straits | B9: Turkey | C9: Bulgaria, Romania, Ukraine, Russia, Georgia | D9: United States, Russia, France, United Kingdom | E9: 57.7 | F9: 45.6 | G9: 35.7 | H9: 59 | I9: =E9*'00_CONFIG'!$C$5+F9*'00_CONFIG'!$C$6+G9*'00_CONFIG'!$C$7+H9*'00_CONFIG'!$C$8 -> 51.505 | J9: =IF(I9<=20,"LOW",IF(I9<=40,"MODERATE",IF(I9<=60,"ELEVATED",IF(I9<=80,"HIGH","CRITICAL")))) -> ELEVATED | K9: None (no bypass exists)
A10: Strait of Gibraltar | B10: Spain, Morocco, United Kingdom | C10: Portugal, Algeria | D10: United States, France, Morocco | E10: 31 | F10: 36.3 | G10: 34.8 | H10: 24 | I10: =E10*'00_CONFIG'!$C$5+F10*'00_CONFIG'!$C$6+G10*'00_CONFIG'!$C$7+H10*'00_CONFIG'!$C$8 -> 32.195 | J10: =IF(I10<=20,"LOW",IF(I10<=40,"MODERATE",IF(I10<=60,"ELEVATED",IF(I10<=80,"HIGH","CRITICAL")))) -> MODERATE | K10: Atlantic open ocean
A11: Cape of Good Hope | B11: South Africa | C11: Namibia, Mozambique, Madagascar | D11: China, United States, France, India | E11: 48.2 | F11: 56.8 | G11: 38.9 | H11: 18 | I11: =E11*'00_CONFIG'!$C$5+F11*'00_CONFIG'!$C$6+G11*'00_CONFIG'!$C$7+H11*'00_CONFIG'!$C$8 -> 45.935 | J11: =IF(I11<=20,"LOW",IF(I11<=40,"MODERATE",IF(I11<=60,"ELEVATED",IF(I11<=80,"HIGH","CRITICAL")))) -> ELEVATED | K11: Primary bypass route
A12: Danish Straits | B12: Denmark, Sweden | C12: Germany, Poland, Norway, Finland, Russia | D12: United States, Russia, United Kingdom, France | E12: 9.3 | F12: 26.2 | G12: 35.7 | H12: 53 | I12: =E12*'00_CONFIG'!$C$5+F12*'00_CONFIG'!$C$6+G12*'00_CONFIG'!$C$7+H12*'00_CONFIG'!$C$8 -> 21.855 | J12: =IF(I12<=20,"LOW",IF(I12<=40,"MODERATE",IF(I12<=60,"ELEVATED",IF(I12<=80,"HIGH","CRITICAL")))) -> MODERATE | K12: None (no bypass exists)
A13: Taiwan Strait | B13: Taiwan, China | C13: Philippines, Japan | D13: United States, Japan, Australia, South Korea, India | E13: 31.4 | F13: 32.1 | G13: 26.5 | H13: 30 | I13: =E13*'00_CONFIG'!$C$5+F13*'00_CONFIG'!$C$6+G13*'00_CONFIG'!$C$7+H13*'00_CONFIG'!$C$8 -> 30.7 | J13: =IF(I13<=20,"LOW",IF(I13<=40,"MODERATE",IF(I13<=60,"ELEVATED",IF(I13<=80,"HIGH","CRITICAL")))) -> MODERATE | K13: Philippine Sea (east of Taiwan)
A14: Korea Strait | B14: South Korea, Japan | C14: North Korea | D14: United States, China, Russia | E14: 17.5 | F14: 59.5 | G14: 47.9 | H14: 27 | I14: =E14*'00_CONFIG'!$C$5+F14*'00_CONFIG'!$C$6+G14*'00_CONFIG'!$C$7+H14*'00_CONFIG'!$C$8 -> 33.51 | J14: =IF(I14<=20,"LOW",IF(I14<=40,"MODERATE",IF(I14<=60,"ELEVATED",IF(I14<=80,"HIGH","CRITICAL")))) -> MODERATE | K14: Sea of Japan / Pacific
A15: Lombok Strait | B15: Indonesia | C15: Australia | D15: China, United States, Japan, Australia | E15: 42.6 | F15: 11.2 | G15: 25.7 | H15: 25 | I15: =E15*'00_CONFIG'!$C$5+F15*'00_CONFIG'!$C$6+G15*'00_CONFIG'!$C$7+H15*'00_CONFIG'!$C$8 -> 30.455 | J15: =IF(I15<=20,"LOW",IF(I15<=40,"MODERATE",IF(I15<=60,"ELEVATED",IF(I15<=80,"HIGH","CRITICAL")))) -> MODERATE | K15: Malacca Strait
... A21: Northern Sea Route | B21: Russia | C21: Norway, Canada, United States | D21: China, France, Japan | E21: 66.6 | F21: 18.1 | G21: 28 | H21: 36 | I21: =E21*'00_CONFIG'!$C$5+F21*'00_CONFIG'!$C$6+G21*'00_CONFIG'!$C$7+H21*'00_CONFIG'!$C$8 -> 45.625 | J21: =IF(I21<=20,"LOW",IF(I21<=40,"MODERATE",IF(I21<=60,"ELEVATED",IF(I21<=80,"HIGH","CRITICAL")))) -> ELEVATED | K21: Traditional Suez / Panama lanes

Sheet ENV_SCORES
A1: ENV_SCORES | Environmental Modifier | Geo x 35% + Weather x 40% + Bypass x 25%
A2: Geography: HyperVolatility + IMO/BIMCO · Weather: ERA5 2023-2026 (ECMWF Copernicus) · Bypass: Fixed analytical assignment
A3: Chokepoint | B3: Width (nm) | C3: Depth (m) | D3: Lanes | E3: GEO (0-100) | F3: SWH (m) | G3: Wind (m/s) | H3: WEATHER (0-100) | I3: BYPASS (0-100) | J3: ENV (0-100) | K3: ENV (0-10) | L3: BAND
A4: Strait of Hormuz | B4: 21 | C4: 80 | D4: 2 | E4: 26 | F4: 0.43 | G4: 1.81 | H4: 8.5 | I4: 100 | J4: 37.5 | K4: 3.8 | L4: MODERATE
A5: Strait of Malacca | B5: 1.5 | C5: 23 | D5: 2 | E5: 63.5 | F5: 0.3 | G5: 0.08 | H5: 8.5 | I5: 40 | J5: 35.6 | K5: 3.6 | L5: MODERATE
A6: Suez Canal | B6: 0.11 | C6: 24 | D6: 1 | E6: 88.5 | F6: 0.53 | G6: 5.55 | H6: 23 | I6: 80 | J6: 60.2 | K6: 6 | L6: HIGH
A7: Bab el-Mandeb | B7: 18 | C7: 186 | D7: 2 | E7: 29 | F7: 0.77 | G7: 3.07 | H7: 18.5 | I7: 80 | J7: 37.5 | K7: 3.8 | L7: MODERATE
A8: Panama Canal | B8: 0.06 | C8: 12.5 | D8: 1 | E8: 96 | F8: 0.41 | G8: 1.9 | H8: 8.5 | I8: 60 | J8: 52 | K8: 5.2 | L8: ELEVATED
A9: Bosphorus / Turkish Straits | B9: 0.38 | C9: 27 | D9: 1 | E9: 75 | F9: 0.85 | G9: 2.19 | H9: 18.5 | I9: 100 | J9: 58.6 | K9: 5.9 | L9: ELEVATED
A10: Strait of Gibraltar | B10: 7 | C10: 300 | D10: 2 | E10: 36.5 | F10: 0.85 | G10: 0.24 | H10: 15.5 | I10: 20 | J10: 24 | K10: 2.4 | L10: MODERATE
A11: Cape of Good Hope | D11: 4 | E11: 0 | F11: 2.5 | G11: 2.13 | H11: 39.5 | I11: 10 | J11: 18.3 | K11: 1.8 | L11: LOW
A12: Danish Straits | B12: 2 | C12: 7 | D12: 2 | E12: 71 | F12: 0.5 | G12: 1.67 | H12: 8.5 | I12: 100 | J12: 53.2 | K12: 5.3 | L12: ELEVATED
A13: Taiwan Strait | B13: 70 | C13: 70 | D13: 2 | E13: 18.5 | F13: 1.65 | G13: 5.57 | H13: 37 | I13: 35 | J13: 30 | K13: 3 | L13: MODERATE
A14: Korea Strait | B14: 25 | C14: 90 | D14: 2 | E14: 26 | F14: 1.06 | G14: 1.53 | H14: 22.5 | I14: 35 | J14: 26.9 | K14: 2.7 | L14: MODERATE
A15: Lombok Strait | B15: 11 | C15: 250 | D15: 2 | E15: 29 | F15: 0.93 | G15: 2.2 | H15: 18.5 | I15: 30 | J15: 25 | K15: 2.5 | L15: MODERATE
A16: Sunda Strait | B16: 15 | C16: 20 | D16: 2 | E16: 48.5 | F16: 0.4 | G16: 0.54 | H16: 8.5 | I16: 30 | J16: 27.9 | K16: 2.8 | L16: MODERATE
A17: Florida Straits | B17: 90 | C17: 150 | D17: 2 | E17: 14 | F17: 0.74 | G17: 3.1 | H17: 18.5 | I17: 25 | J17: 18.6 | K17: 1.9 | L17: LOW
A18: Windward Passage | B18: 50 | D18: 2 | E18: 11 | F18: 1.11 | G18: 5.51 | H18: 30 | I18: 35 | J18: 24.6 | K18: 2.5 | L18: MODERATE
A19: Strait of Magellan | B19: 1.4 | C19: 20 | D19: 1 | E19: 73.5 | F19: 0.84 | G19: 5.37 | H19: 23 | I19: 20 | J19: 39.9 | K19: 4 | L19: MODERATE
A20: Cape Horn | D20: 4 | E20: 0 | F20: 2.7 | G20: 7.15 | H20: 57 | I20: 20 | J20: 27.8 | K20: 2.8 | L20: MODERATE
A21: Northern Sea Route | B21: 50 | C21: 15 | D21: 1 | E21: 43.5 | F21: 0.54 | G21: 0.73 | H21: 15.5 | I21: 60 | J21: 36.4 | K21: 3.6 | L21: MODERATE

Sheet COUNTRY_RISK
A1: COUNTRY_RISK | ACLED Conflict Metrics + Six-Pillar Aggregates
A2: Left block: raw ACLED counts. Right block: normalized pillar sub-scores. Country Risk = weighted average per 00_CONFIG.
A3: Country | B3: ISO2 | C3: PV Events 2024–2026 | D3: PV Events 2026 | E3: Fatalities 2024–2026 | F3: Civilian Events 2024–2026 | G3: P1 Gov | H3: P2 Econ | I3: P3 Sec | J3: P4 Stab | K3: P5 Ext | L3: P6 Infra | M3: COUNTRY RISK | N3: BAND
A4: Algeria | B4: DZ | C4: 96 | D4: 19 | E4: 53 | F4: 8 | G4: 78.5 | H4: 41.3 | I4: 49.2 | J4: 67.4 | K4: 68.2 | L4: 26.9 | M4: 56.1 | N4: ELEVATED
A5: Argentina | B5: AR | C5: 1819 | D5: 531 | E5: 9 | F5: 2 | G5: 52.8 | H5: 38.5 | I5: 16.8 | J5: 42.8 | K5: 22.2 | L5: 19.2 | M5: 32.3 | N5: MODERATE
A6: Australia | B6: AU | C6: 723 | D6: 98 | E6: 16 | F6: 0 | G6: 9 | H6: 13 | I6: 16.2 | J6: 5.8 | K6: 19.2 | L6: 2.8 | M6: 11.2 | N6: LOW
A7: Bahamas | B7: BS | C7: 11 | D7: 0 | E7: 0 | F7: 1 | G7: 36.1 | H7: 32.2 | I7: 24.4 | J7: 18.2 | K7: 37.2 | L7: 8.8 | M7: 26.6 | N7: MODERATE
A8: Bahrain | B8: BH | C8: 945 | D8: 388 | E8: 3 | F8: 11 | G8: 70.9 | H8: 34.1 | I8: 27.6 | J8: 60.8 | K8: 36.8 | L8: 12 | M8: 41.3 | N8: ELEVATED
A9: Bulgaria | B9: BG | C9: 797 | D9: 96 | E9: 0 | F9: 1 | G9: 46.6 | H9: 16.5 | I9: 15.5 | J9: 37.4 | K9: 17.5 | L9: 14.2 | M9: 25.3 | N9: MODERATE
A10: Canada | B10: CA | C10: 1472 | D10: 314 | E10: 7 | F10: 2 | G10: 10.6 | H10: 32.8 | I10: 14.8 | J10: 6 | K10: 17.5 | L10: 5 | M10: 14.3 | N10: LOW
A11: Chile | B11: CL | C11: 1281 | D11: 279 | E11: 12 | F11: 47 | G11: 25.2 | H11: 29.1 | I11: 43.6 | J11: 35.2 | K11: 40.6 | L11: 15.8 | M11: 31.9 | N11: MODERATE
A12: China | B12: CN | C12: 1576 | D12: 302 | E12: 2 | F12: 165 | G12: 78.5 | H12: 34.2 | I12: 33.1 | J12: 63.4 | K12: 38.7 | L12: 18.8 | M12: 45.6 | N12: ELEVATED
A13: Colombia | B13: CO | C13: 5681 | D13: 1224 | E13: 2193 | F13: 1235 | G13: 56.3 | H13: 38.9 | I13: 70.2 | J13: 74.5 | K13: 64.4 | L13: 22.7 | M13: 55.4 | N13: ELEVATED
A14: Costa Rica | B14: CR | C14: 127 | D14: 39 | E14: 2 | F14: 9 | G14: 25.7 | H14: 34.3 | I14: 31.1 | J14: 13.6 | K14: 44.4 | L14: 15.8 | M14: 27.6 | N14: MODERATE
A15: Cuba | B15: CU | C15: 323 | D15: 172 | E15: 14 | F15: 38 | G15: 77.2 | H15: 2.9 | I15: 43.8 | J15: 40.9 | K15: 49.9 | L15: 0 | M15: 38.3 | N15: MODERATE
... A61: Thailand | B61: TH | C61: 476 | D61: 78 | E61: 107 | F61: 32 | G61: 57.2 | H61: 27.1 | I61: 41.6 | J61: 58.4 | K61: 37.3 | L61: 25 | M61: 41.9 | N61: ELEVATED
A62: Turkey | B62: TR | C62: 6128 | D62: 1198 | E62: 16 | F62: 15 | G62: 77.7 | H62: 43.7 | I62: 62.9 | J62: 79.6 | K62: — | L62: 16.4 | M62: 57.7 | N62: ELEVATED
A63: Ukraine | B63: UA | C63: 84228 | D63: 17503 | E63: 71612 | F63: 81 | G63: 66.5 | H63: 50.7 | I63: 80.2 | J63: 89.6 | K63: 100 | L63: 26.4 | M63: 69.3 | N63: HIGH
A64: United Arab Emirates | B64: AE | C64: 232 | D64: 220 | E64: 13 | F64: 1 | G64: 54.2 | H64: 9.7 | I64: 15.5 | J64: 20.1 | K64: 32.9 | L64: 6 | M64: 24.2 | N64: MODERATE
A65: United Kingdom | B65: GB | C65: 1057 | D65: 242 | E65: 3 | F65: 10 | G65: 14.8 | H65: 25.3 | I65: 24.9 | J65: 27.8 | K65: 28.4 | L65: 4.8 | M65: 20.9 | N65: MODERATE
A66: United States | B66: US | C66: 20427 | D66: 4498 | E66: 48 | F66: 39 | G66: 22.6 | H66: 29.1 | I66: 47.9 | J66: 38.6 | K66: 47.2 | L66: 0.6 | M66: 31.4 | N66: MODERATE
A67: Vietnam | B67: VN | C67: 0 | D67: 0 | E67: 0 | F67: 0 | G67: 74.6 | H67: 24.3 | I67: 17.5 | J67: 47.4 | K67: 33.8 | L67: 29.4 | M67: 38.7 | N67: MODERATE
A68: Yemen | B68: YE | C68: 10760 | D68: 1424 | E68: 2022 | F68: 857 | G68: 100 | H68: 70.9 | I68: 84.8 | J68: 100 | K68: 71.2 | L68: 71.2 | M68: 84 | N68: CRITICAL

Sheet PILLAR_SCORES
A1: PILLAR_SCORES | Six Normalized Pillar Sub-Scores + Weighted Country Risk
A2: Each pillar is the average of its normalized indicators (0-100, higher = higher risk). COUNTRY RISK is the weighted average per 00_CONFIG using python to write to the workbook.
A3: Country | B3: ISO2 | C3: P1: Gov | D3: P2: Econ | E3: P3: Sec | F3: P4: Stab | G3: P5: Ext | H3: P6: Infra | I3: COUNTRY RISK | J3: BAND
A4: Algeria | B4: DZ | C4: 78.5 | D4: 41.3 | E4: 49.2 | F4: 67.4 | G4: 68.2 | H4: 26.9 | I4: 56.1 | J4: ELEVATED
A5: Argentina | B5: AR | C5: 52.8 | D5: 38.5 | E5: 16.8 | F5: 42.8 | G5: 22.2 | H5: 19.2 | I5: 32.3 | J5: MODERATE
A6: Australia | B6: AU | C6: 9 | D6: 13 | E6: 16.2 | F6: 5.8 | G6: 19.2 | H6: 2.8 | I6: 11.2 | J6: LOW
A7: Bahamas | B7: BS | C7: 36.1 | D7: 32.2 | E7: 24.4 | F7: 18.2 | G7: 37.2 | H7: 8.8 | I7: 26.6 | J7: MODERATE
A8: Bahrain | B8: BH | C8: 70.9 | D8: 34.1 | E8: 27.6 | F8: 60.8 | G8: 36.8 | H8: 12 | I8: 41.3 | J8: ELEVATED
A9: Bulgaria | B9: BG | C9: 46.6 | D9: 16.5 | E9: 15.5 | F9: 37.4 | G9: 17.5 | H9: 14.2 | I9: 25.3 | J9: MODERATE
A10: Canada | B10: CA | C10: 10.6 | D10: 32.8 | E10: 14.8 | F10: 6 | G10: 17.5 | H10: 5 | I10: 14.3 | J10: LOW
A11: Chile | B11: CL | C11: 25.2 | D11: 29.1 | E11: 43.6 | F11: 35.2 | G11: 40.6 | H11: 15.8 | I11: 31.9 | J11: MODERATE
A12: China | B12: CN | C12: 78.5 | D12: 34.2 | E12: 33.1 | F12: 63.4 | G12: 38.7 | H12: 18.8 | I12: 45.6 | J12: ELEVATED
A13: Colombia | B13: CO | C13: 56.3 | D13: 38.9 | E13: 70.2 | F13: 74.5 | G13: 64.4 | H13: 22.7 | I13: 55.4 | J13: ELEVATED
A14: Costa Rica | B14: CR | C14: 25.7 | D14: 34.3 | E14: 31.1 | F14: 13.6 | G14: 44.4 | H14: 15.8 | I14: 27.6 | J14: MODERATE
A15: Cuba | B15: CU | C15: 77.2 | D15: 2.9 | E15: 43.8 | F15: 40.9 | G15: 49.9 | H15: 0 | I15: 38.3 | J15: MODERATE
... A61: Thailand | B61: TH | C61: 57.2 | D61: 27.1 | E61: 41.6 | F61: 58.4 | G61: 37.3 | H61: 25 | I61: 41.9 | J61: ELEVATED
A62: Turkey | B62: TR | C62: 77.7 | D62: 43.7 | E62: 62.9 | F62: 79.6 | G62: N/A | H62: 16.4 | I62: 57.7 | J62: ELEVATED
A63: Ukraine | B63: UA | C63: 66.5 | D63: 50.7 | E63: 80.2 | F63: 89.6 | G63: 100 | H63: 26.4 | I63: 69.3 | J63: HIGH
A64: United Arab Emirates | B64: AE | C64: 54.2 | D64: 9.7 | E64: 15.5 | F64: 20.1 | G64: 32.9 | H64: 6 | I64: 24.2 | J64: MODERATE
A65: United Kingdom | B65: GB | C65: 14.8 | D65: 25.3 | E65: 24.9 | F65: 27.8 | G65: 28.4 | H65: 4.8 | I65: 20.9 | J65: MODERATE
A66: United States | B66: US | C66: 22.6 | D66: 29.1 | E66: 47.9 | F66: 38.6 | G66: 47.2 | H66: 0.6 | I66: 31.4 | J66: MODERATE
A67: Vietnam | B67: VN | C67: 74.6 | D67: 24.3 | E67: 17.5 | F67: 47.4 | G67: 33.8 | H67: 29.4 | I67: 38.7 | J67: MODERATE
A68: Yemen | B68: YE | C68: 100 | D68: 70.9 | E68: 84.8 | F68: 100 | G68: 71.2 | H68: 71.2 | I68: 84 | J68: CRITICAL

Sheet RAW_INDICATORS
A1: RAW_INDICATORS | All Source Values Before Scoring
A2: Every raw value from every source, one row per country.
A3: Country | B3: ISO2 | C3: CPI | D3: Democracy | E3: Rule of Law | F3: Freedom | G3: GDP/cap USD | H3: Inflation % | I3: Unemp % | J3: Debt/GDP % | K3: GPI | L3: Terror Idx | M3: Mil %GDP | N3: PV Events 3yr | O3: Pol Stab %ile | P3: FSI Total | Q3: Electricity %
A4: Algeria | B4: DZ | C4: 34 | D4: 3.55 | E4: 0.49 | F4: 4.5 | G4: 6628.405 | I4: 11.5 | J4: 46.2 | K4: 2.042 | L4: 2.415 | M4: 21.38 | N4: 57 | O4: 23.2 | P4: 70 | Q4: 100
A5: Argentina | B5: AR | C5: 36 | D5: 6.51 | E5: 0.54 | F5: 6.91 | G5: 14356.62 | I5: 7.9 | J5: 83.2 | K5: 1.768 | L5: 0.801 | M5: 1.93 | N5: 91 | O5: 41.7 | P5: 46.4 | Q5: 100
A6: Australia | B6: AU | C6: 76 | D6: 8.85 | E6: 0.8 | F6: 8.79 | G6: 75647.84 | I6: 4.1 | J6: 43.8 | K6: 1.505 | L6: 1.973 | M6: 4.96 | N6: 10 | O6: 79.6 | P6: 22 | Q6: 100
A7: Bahamas | B7: BS | C7: 64 | E7: 0.58 | F7: 7.79 | G7: 40892.45 | I7: 8.5 | J7: 81.5 | N7: 11 | O7: 84.8 | P7: 49.2 | Q7: 100
A8: Bahrain | B8: BH | C8: 50 | D8: 2.45 | F8: 5.44 | G8: 29569.16 | I8: 1.2 | J8: 134 | K8: 2.099 | L8: 0.059 | M8: 10.22 | N8: 27 | O8: 29.4 | P8: 65.1 | Q8: 100
A9: Bulgaria | B9: BG | C9: 40 | D9: 6.34 | E9: 0.55 | F9: 7.85 | G9: 23848.46 | I9: 4.2 | J9: 24.1 | K9: 1.61 | M9: 5.49 | N9: 5 | O9: 55.5 | P9: 51.8 | Q9: 100
A10: Canada | B10: CA | C10: 75 | D10: 8.69 | E10: 0.79 | F10: 8.74 | G10: 60304.56 | I10: 6.5 | J10: 111 | K10: 1.491 | L10: 1.87 | M10: 3.08 | N10: 19 | O10: 76.3 | P10: 18.9 | Q10: 100
A11: Chile | B11: CL | C11: 63 | D11: 7.83 | E11: 0.66 | F11: 8.47 | G11: 20239.76 | I11: 9.1 | J11: 41.7 | K11: 1.899 | L11: 5.162 | M11: 5.84 | N11: 541 | O11: 50.2 | P11: 42.2 | Q11: 100
A12: China | B12: CN | C12: 43 | D12: 2.11 | E12: 0.48 | F12: 4.93 | G12: 14873.57 | I12: 4.6 | J12: 88.3 | K12: 2.093 | L12: 1.863 | M12: 5.06 | N12: 553 | O12: 25.1 | P12: 65.1 | Q12: 100
A13: Colombia | B13: CO | C13: 37 | D13: 6.35 | E13: 0.47 | F13: 6.91 | G13: 10103.71 | I13: 9.7 | J13: 61.3 | K13: 2.695 | L13: 6.381 | M13: 10.12 | N13: 8100 | O13: 19 | P13: 78.1 | Q13: 100
A14: Costa Rica | B14: CR | C14: 56 | D14: 8.29 | E14: 0.68 | F14: 8.36 | G14: 20299.19 | I14: 7.9 | J14: 74.18 | K14: 1.843 | N14: 50 | O14: 83.9 | P14: 40.4 | Q14: 100
A15: Cuba | B15: CU | C15: 40 | D15: 2.58 | I15: 1.6 | K15: 2.123 | N15: 157 | O15: 56.9 | P15: 59.5 | Q15: 100
A16: Denmark | B16: DK | C16: 89 | D16: 9.28 | E16: 0.9 | F16: 9.03 | G16: 83445.33 | I16: 5.6 | J16: 31.1 | K16: 1.393 | L16: 0.72 | M16: 5.06 | N16: 5 | O16: 76.8 | P16: 17.9 | Q16: 100
A17: Djibouti | B17: DJ | C17: 31 | D17: 2.7 | F17: 5.44 | G17: 4420.745 | I17: 25.9 | K17: 2.276 | L17: 1.461 | N17: 11 | O17: 24.6 | P17: 82.2 | Q17: 65
A18: Dominican Republic | B18: DO | C18: 37 | D18: 6.62 | E18: 0.5 | F18: 7.9 | G18: 12405.59 | I18: 5.5 | J18: 46.2 | K18: 1.996 | M18: 4.04 | N18: 83 | O18: 53.6 | P18: 60.8 | Q18: 98.1
A19: Egypt | B19: EG | C19: 30 | D19: 2.79 | E19: 0.35 | F19: 4.08 | G19: 3903.808 | I19: 7.2 | J19: 82.9 | K19: 2.157 | L19: 4.416 | M19: 2.93 | N19: 101 | O19: 16.6 | P19: 81.6 | Q19: 100
A20: Eritrea | B20: ER | C20: 13 | D20: 1.97 | I20: 5.6 | J20: 164 | K20: 2.542 | N20: 5 | O20: 17.5 | P20: 94.5 | Q20: 55.4
A21: Ethiopia | B21: ET | C21: 38 | D21: 3.24 | E21: 0.36 | F21: 4.7 | G21: 1081.49 | I21: 3.4 | J21: 32 | K21: 2.688 | L21: 0.787 | M21: 6.91 | N21: 6237 | O21: 6.2 | P21: 100.4 | Q21: 55
A22: Finland | B22: FI | C22: 88 | D22: 9.3 | E22: 0.87 | F22: 8.83 | G22: 60129.69 | I22: 8.3 | J22: 82.1 | K22: 1.42 | L22: 0.949 | M22: 4.05 | N22: 4 | O22: 71.1 | P22: 16 | Q22: 100
A23: France | B23: FR | C23: 66 | D23: 7.99 | E23: 0.72 | F23: 8.18 | G23: 52083.33 | H23: 0.3 | I23: 7.4 | J23: 113 | K23: 1.967 | L23: 2.712 | M23: 3.59 | N23: 230 | O23: 55.9 | P23: 28.8 | Q23: 100
A24: Georgia | B24: GE | C24: 50 | D24: 4.7 | E24: 0.58 | F24: 7.52 | G24: 11574.01 | H24: 4.8 | I24: 11.5 | J24: 36.1 | K24: 2.185 | M24: 6.07 | N24: 64 | O24: 33.2 | P24: 71.9 | Q24: 100
A25: Germany | B25: DE | C25: 77 | D25: 8.73 | E25: 0.83 | F25: 8.67 | G25: 65302.89 | H25: 2.1 | I25: 3.5 | J25: 62.2 | K25: 1.533 | L25: 4.748 | M25: 3.93 | N25: 191 | O25: 66.4 | P25: 24.6 | Q25: 100
A26: Haiti | B26: HT | C26: 16 | D26: 2.74 | E26: 0.32 | F26: 5.85 | G26: 3078.902 | I26: 15.1 | J26: 14 | K26: 2.731 | M26: 1.63 | N26: 4413 | O26: 10.4 | P26: 102.9 | Q26: 49.3
A27: India | B27: IN | C27: 39 | D27: 7.29 | E27: 0.49 | F27: 6.26 | G27: 2812.623 | I27: 4.3 | J27: 81.92 | K27: 2.229 | L27: 6.411 | M27: 7.63 | N27: 9921 | O27: 21.3 | P27: 74.1 | Q27: 99.2
A28: Indonesia | B28: ID | C28: 34 | D28: 6.44 | E28: 0.52 | F28: 6.67 | G28: 5361.7 | H28: 3.55 | I28: 3.3 | J28: 38.8 | K28: 1.786 | L28: 4.17 | M28: 4.6 | N28: 1452 | O28: 28.9 | P28: 65.6 | Q28: 100
A29: Iran | B29: IR | C29: 23 | D29: 1.96 | E29: 0.38 | F29: 3.78 | G29: 3414.979 | I29: 9.2 | J29: 36.8 | K29: 2.75 | L29: 6.056 | M29: 12.55 | N29: 983 | O29: 8.1 | P29: 85.4 | Q29: 100
A30: Iraq | B30: IQ | C30: 28 | D30: 2.8 | F30: 4.92 | G30: 5677.195 | I30: 15.6 | J30: 42.9 | K30: 2.862 | L30: 6.582 | M30: 4.87 | N30: 14408 | O30: 2.4 | P30: 91.4 | Q30: 100
A31: Israel | B31: IL | C31: 62 | D31: 7.8 | F31: 7.52 | G31: 69803.85 | I31: 3.2 | J31: 69 | K31: 3.108 | L31: 7.463 | M31: 19.99 | N31: 4658 | O31: 10 | P31: 44.1 | Q31: 100
A32: Jamaica | B32: JM | C32: 44 | D32: 6.74 | E32: 0.57 | F32: 7.89 | G32: 8355.758 | I32: 4.9 | J32: 67.9 | K32: 2.047 | M32: 4.07 | N32: 1058 | O32: 57.3 | P32: 61.9 | Q32: 100
A33: Japan | B33: JP | C33: 71 | D33: 8.48 | E33: 0.78 | F33: 8.6 | G33: 35703.43 | I33: 2.6 | J33: 237 | K33: 1.44 | L33: 0.949 | M33: 3.25 | N33: 2 | O33: 81.5 | P33: 30.5 | Q33: 100
A34: Jordan | B34: JO | C34: 50 | D34: 3.28 | E34: 0.55 | F34: 6.63 | G34: 5600.661 | I34: 18 | J34: 90.2 | K34: 1.957 | L34: 2.913 | M34: 14.35 | N34: 41 | O34: 40.3 | P34: 75.7 | Q34: 100
A35: Kuwait | B35: KW | C35: 46 | D35: 2.78 | E35: 0.58 | F35: 6.18 | G35: 33164.45 | I35: 2.2 | J35: 3 | K35: 1.642 | M35: 9.68 | N35: 0 | O35: 58.8 | P35: 51.2 | Q35: 100
A36: Libya | B36: LY | C36: 13 | D36: 2.31 | F36: 4.67 | G36: 6962.074 | I36: 18.7 | K36: 2.478 | L36: 1.612 | N36: 676 | O36: 4.3 | P36: 96.1 | Q36: 70
A37: Madagascar | B37: MG | C37: 25 | D37: 5.33 | E37: 0.43 | F37: 6.8 | G37: 655.51 | I37: 3.1 | J37: 38.8 | K37: 1.895 | M37: 4.24 | N37: 1277 | O37: 19.9 | P37: 81.7 | Q37: 36.1
A38: Malaysia | B38: MY | C38: 52 | D38: 7.11 | E38: 0.57 | F38: 7.11 | G38: 15085.38 | I38: 3.9 | J38: 70.4 | K38: 1.469 | L38: 1.626 | M38: 4.52 | N38: 15 | O38: 50.7 | P38: 55 | Q38: 100
A39: Mexico | B39: MX | C39: 27 | D39: 5.32 | E39: 0.4 | F39: 6.72 | G39: 15779.32 | I39: 2.8 | J39: 49.7 | K39: 2.636 | L39: 0.582 | M39: 2.97 | N39: 22357 | O39: 22.7 | P39: 69.8 | Q39: 100
A40: Morocco | B40: MA | C40: 39 | D40: 4.97 | E40: 0.48 | F40: 5.44 | G40: 5107.302 | I40: 9 | J40: 70 | K40: 2.012 | M40: 10.67 | N40: 158 | O40: 29.9 | P40: 68.2 | Q40: 100
A41: Mozambique | B41: MZ | C41: 21 | D41: 3.38 | E41: 0.37 | F41: 6.52 | G41: 632.042 | I41: 3.6 | J41: 76.9 | K41: 2.273 | L41: 6.251 | M41: 6.13 | N41: 1064 | O41: 11.8 | P41: 94 | Q41: 33.2
A42: Namibia | B42: NA | C42: 46 | D42: 6.48 | E42: 0.61 | F42: 7.5 | G42: 5572.98 | I42: 19.2 | J42: 65.3 | K42: 1.789 | M42: 7.13 | N42: 17 | O42: 63.5 | P42: 60.3 | Q42: 56.2
A43: North Korea | B43: KP | C43: 15 | D43: 1.08 | I43: 2.9 | K43: 2.911 | N43: 9 | O43: 30.3 | P43: 87 | Q43: 54.7
A44: Norway | B44: NO | C44: 81 | D44: 9.81 | E44: 0.89 | F44: 8.69 | G44: 105876.9 | I44: 4 | J44: 55.1 | K44: 1.644 | L44: 1.198 | M44: 4.53 | N44: 8 | O44: 77.7 | P44: 14.5 | Q44: 100
A45: Oman | B45: OM | C45: 52 | D45: 3.05 | F45: 5.71 | G45: 21644.87 | I45: 3.2 | J45: 35.5 | K45: 1.738 | L45: 2.927 | M45: 20.13 | N45: 5 | O45: 65.9 | P45: 48.7 | Q45: 100
A46: Panama | B46: PA | C46: 33 | D46: 6.84 | E46: 0.52 | F46: 7.92 | G46: 20563.59 | I46: 6.6 | J46: 56.6 | K46: 2.006 | N46: 34 | O46: 52.6 | P46: 48.7 | Q46: 95
A47: Philippines | B47: PH | C47: 32 | D47: 6.63 | E47: 0.46 | F47: 6.6 | G47: 4442.551 | I47: 2.2 | J47: 60.7 | K47: 2.148 | L47: 5.166 | M47: 5.44 | N47: 1946 | O47: 23.7 | P47: 77.8 | Q47: 94.8
A48: Poland | B48: PL | C48: 53 | D48: 7.4 | E48: 0.66 | F48: 7.76 | G48: 31335.95 | I48: 2.5 | J48: 55.1 | K48: 1.713 | L48: 1.962 | M48: 8.47 | N48: 172 | O48: 64 | P48: 45.2 | Q48: 100
A49: Portugal | B49: PT | C49: 56 | D49: 8.08 | E49: 0.67 | F49: 8.62 | G49: 35433.54 | H49: 1.9 | I49: 6.4 | J49: 93.6 | K49: 1.371 | M49: 3.57 | N49: 7 | O49: 70.6 | P49: 25.7 | Q49: 100
A50: Qatar | B50: QA | C50: 58 | D50: 3.17 | E50: 0.62 | F50: 5.49 | G50: 68138.3 | I50: 0.2 | J50: 40.8 | K50: 1.593 | N50: 2 | O50: 84.4 | P50: 40.5 | Q50: 100
A51: Romania | B51: RO | C51: 45 | D51: 5.99 | E51: 0.61 | F51: 8.06 | G51: 25692.97 | I51: 5.4 | J51: 54.8 | K51: 1.721 | M51: 5.85 | N51: 25 | O51: 56.4 | P51: 53 | Q51: 100
A52: Russia | B52: RU | C52: 22 | D52: 2.03 | E52: 0.41 | F52: 4.86 | G52: 18525.49 | I52: 2.6 | J52: 16.4 | K52: 3.441 | L52: 6.267 | M52: 18.9 | N52: 32911 | O52: 13.3 | P52: 80.7 | Q52: 100
A53: Saudi Arabia | B53: SA | C53: 57 | D53: 2.08 | F53: 4.97 | G53: 37811.37 | I53: 3.9 | J53: 26.2 | K53: 2.035 | L53: 0.845 | M53: 22.31 | N53: 14 | O53: 39.8 | P53: 65.3 | Q53: 100
A54: Singapore | B54: SG | C54: 84 | D54: 6.18 | E54: 0.78 | F54: 7.73 | G54: 107758 | I54: 3.2 | J54: 173 | K54: 1.357 | M54: 20.13 | N54: 0 | O54: 97.2 | P54: 25.5 | Q54: 100
A55: Somalia | B55: SO | C55: 9 | F55: 4.87 | G55: 812.86 | I55: 18.9 | K55: 2.983 | L55: 7.614 | M55: 21.57 | N55: 10447 | O55: 2.8 | P55: 111.9 | Q55: 48.9
A56: South Africa | B56: ZA | C56: 41 | D56: 7.16 | E56: 0.56 | F56: 7.07 | G56: 7502.97 | I56: 33.2 | J56: 76.9 | K56: 2.347 | M56: 2.11 | N56: 1025 | O56: 20.9 | P56: 72 | Q56: 86.5
A57: South Korea | B57: KR | C57: 63 | D57: 7.75 | E57: 0.74 | F57: 8.15 | G57: 37412.08 | H57: 2 | I57: 2.7 | J57: 46.8 | K57: 1.736 | L57: 0.582 | M57: 11.32 | N57: 9 | O57: 68.2 | P57: 31.5 | Q57: 100
A58: Spain | B58: ES | C58: 55 | D58: 8.13 | E58: 0.71 | F58: 8.37 | G58: 41563.18 | H58: 2.4 | I58: 11.4 | J58: 102 | K58: 1.578 | L58: 1.256 | M58: 3.2 | N58: 50 | O58: 55 | P58: 43.5 | Q58: 100
A59: Sweden | B59: SE | C59: 80 | D59: 9.39 | E59: 0.85 | F59: 8.74 | G59: 70675.66 | I59: 8.6 | J59: 34 | K59: 1.709 | L59: 1.842 | M59: 4.12 | N59: 11 | O59: 73.5 | P59: 20.6 | Q59: 100
A60: Taiwan | B60: TW | C60: 68 | D60: 8.78 | F60: 8.72 | G60: 42102.7 | I60: 3.4 | K60: 1.73 | M60: 12.06 | N60: 0 | O60: 74.4
A61: Thailand | B61: TH | C61: 33 | D61: 6.27 | E61: 0.5 | F61: 6.79 | G61: 8105.068 | I61: 0.7 | J61: 63.7 | K61: 2.017 | L61: 4.63 | M61: 4.54 | N61: 540 | O61: 36 | P61: 68 | Q61: 99.9
A62: Turkey | B62: TR | C62: 31 | D62: 4.26 | E62: 0.41 | F62: 5.1 | G62: 19018.18 | H62: 30.65 | I62: 8.5 | J62: 24.7 | K62: 2.852 | L62: 3.968 | N62: 674 | O62: 13.7 | P62: 81.2 | Q62: 100
A63: Ukraine | B63: UA | C63: 36 | D63: 4.9 | E63: 0.48 | F63: 5.87 | G63: 6980.118 | J63: 89.8 | K63: 3.434 | L63: 2.003 | M63: 54.01 | N63: 184112 | O63: 10.9 | P63: 95.9 | Q63: 100
A64: United Arab Emirates | B64: AE | C64: 69 | D64: 3.07 | E64: 0.64 | F64: 5.81 | G64: 54214.4 | I64: 2.2 | J64: 32.1 | K64: 1.812 | L64: 1.178 | N64: 4 | O64: 70.1 | P64: 37 | Q64: 100
A65: United Kingdom | B65: GB | C65: 70 | D65: 8.34 | E65: 0.78 | F65: 8.6 | G65: 61056.1 | I65: 4.2 | J65: 93.6 | K65: 1.634 | L65: 2.639 | M65: 5.25 | N65: 61 | O65: 62.1 | P65: 41.9 | Q65: 100
A66: United States | B66: US | C66: 64 | D66: 7.85 | E66: 0.68 | F66: 8.71 | G66: 94429.75 | I66: 4.2 | J66: 124 | K66: 2.443 | L66: 3.517 | M66: 9.11 | N66: 402 | O66: 47.4 | P66: 45.3 | Q66: 100
A67: Vietnam | B67: VN | C67: 41 | D67: 2.62 | E67: 0.5 | F67: 5.29 | G67: 5115.236 | I67: 1.5 | J67: 32.9 | K67: 1.721 | N67: 5 | O67: 45 | P67: 58.3 | Q67: 100
A68: Yemen | B68: YE | C68: 13 | D68: 1.95 | F68: 3.98 | G68: 383.749 | I68: 17.1 | J68: 70.9 | K68: 3.262 | L68: 5.08 | N68: 11914 | O68: 0.9 | P68: 108.9 | Q68: 76

Sheet DATA_CIA
A1: DATA_CIA | CIA World Factbook: Chokepoint Countries Only
A2: Static reference layer. Sourced from my CIA_FACTBOOK.xlsm (scraped the entire site with VBA before it was discountinued).
A3: Country | B3: Location | C3: Economic Overview | D3: Military & Security | E3: GDP (PPP) | F3: Urbanization | G3: Electricity Access | H3: Airports
A4: Algeria | B4: Northern Africa, bordering the Mediterranean Sea, between Morocco and Tunisia | C4: suffering oil and gas economy; lack of sector and market diversification; political instability chilling domestic consumption; poor credit access and declines in business confidence; COVID-19 austerity policies; delayed promised socio-economic reforms | D4: Algerian People's National Army (ANP): Land Forces, Naval Forces (includes Coast Guard), Air Forces, Territorial Air Defense Forces, Republican Guard, National GendarmerieMinistry of Interior: General Directorate of National Security (national police) (2025) note: the Republican Guard is subordinate to the ANP, but responsible to the President; the | E4: $699.818 billion (2023 est.) $672.256 billion (2022 est.) $648.896 billion (2021 est.) note: data in 2021 dollars | F4: urban population: 75.3% of total population (2023) rate of urbanization: 1.99% annual rate of change (2020-25 est.) | G4: electrification - total population: 100% (2022 est.) electrification - urban areas: 100% electrification - rural areas: 99.3% | H4: Africa
A5: Argentina | B5: Southern South America, bordering the South Atlantic Ocean, between Chile and Uruguay | C5: large diversified economy; financial risks from debt obligations, rapid inflation, and reduced investor appetites; resource-rich, export-led growth model; increasing trade relations with China; G20 and OAS leader; tendency to nationalize businesses and under-report inflation | D5: Armed Forces of the Argentine Republic (Fuerzas Armadas de la Rep&uacute;blica Argentina): Argentine Army (Ejercito Argentino, EA), Navy of the Argentine Republic (Armada Republica, ARA; includes naval aviation and naval infantry), Argentine Air Force (Fuerza Aerea Argentina, FAA)Ministry of Security: Gendarmer&iacute;a Nacional Argentina (National | E5: $1.234 trillion (2023 est.) $1.255 trillion (2022 est.) $1.192 trillion (2021 est.) note: data in 2021 dollars | F5: urban population: 92.5% of total population (2023) rate of urbanization: 0.97% annual rate of change (2020-25 est.) | G5: electrification - total population: 100% (2022 est.) | H5: South America
A6: Australia | B6: Oceania, continent between the Indian Ocean and the South Pacific Ocean | C6: high-income and globally integrated economy; strong mining, manufacturing, and service sectors driving slow but steady growth; net exporter, driven by commodities to East Asian trade partners; weak productivity and aging population straining labor force participation | D6: Australian Defense Force (ADF): Australian Army, Royal Australian Navy, Royal Australian Air Force (2025) note: the Australian Federal Police (AFP) is an independent agency of the Attorney-General&rsquo;s Department; the AFP, state, and territorial police forces are responsible for internal security; the Australian Border Force (ABF) is under the D | E6: $1.588 trillion (2023 est.) $1.535 trillion (2022 est.) $1.472 trillion (2021 est.) note: data in 2021 dollars | F6: urban population: 86.6% of total population (2023) rate of urbanization: 1.27% annual rate of change (2020-25 est.) note: data include Christmas Island, Cocos Islands, and Norfolk | G6: electrification - total population: 100% (2022 est.) | H6: Australia and Oceania
A7: Bahamas | B7: chain of islands in the North Atlantic Ocean, southeast of Florida, northeast of Cuba; note - although The Bahamas does not border the Caribbean Sea, geopolitically it is often designated as a Caribbe | C7: high-income tourism and financial services economy; major income inequality; strong US bilateral relations; several tax relief programs; targeted investment in agriculture, energy, light manufacturing, and technology industries | D7: Royal Bahamas Defense Force (RBDF): includes land, air, maritime elements; Royal Bahamas Police Force (RBPF) (2025) note: the RBPF maintains internal security; both the RBDF and the RBPF, as well as the Department of Corrections, report to the Minister of National Security | E7: $13.224 billion (2023 est.) $12.884 billion (2022 est.) $11.63 billion (2021 est.) note: data in 2021 dollars | F7: urban population: 83.6% of total population (2023) rate of urbanization: 1.02% annual rate of change (2020-25 est.) | G7: electrification - total population: 100% (2022 est.) | H7: Central America and the Caribbean
A8: Bahrain | B8: Middle East, archipelago in the Persian Gulf, east of Saudi Arabia | C8: high-income, growing Middle Eastern island economy; oil and aluminum exporter with diversification led by services, construction and manufacturing; regional finance and tourism hub; high public debt linked to oil revenue dependence and limited tax base; vulnerable to water reservoir depletion | D8: Bahrain Defense Force (BDF): Royal Bahraini Army (includes the Royal Guard), Royal Bahraini Navy, Royal Bahraini Air ForceMinistry of Interior: National Guard, Special Security Forces Command (SSFC), Coast Guard<span style=\ | E8: $90.228 billion (2023 est.) $87.617 billion (2022 est.) $82.672 billion (2021 est.) note: data in 2021 dollars | F8: urban population: 89.9% of total population (2023) rate of urbanization: 1.99% annual rate of change (2020-25 est.) | G8: electrification - total population: 100% (2022 est.) | H8: Middle East
A9: Bulgaria | B9: Southeastern Europe, bordering the Black Sea, between Romania and Turkey | C9: upper-middle-income EU economy; currency pegged to the euro, with eurozone accession pending; declining energy prices helping lower inflation rate; EU structural funds contributing to investment recovery; skilled labor shortage driven by emigration and aging population | D9: Bulgarian Armed Forces (aka Bulgarian Army): Land Forces, Air Force, NavyMinistry of Interior: General Directorate National Police (GDNP), General Directorate Border Police (GDBP), Special Unit for Combating Terrorism (SOBT) (2025) note 1: the Bulgarian military also has a Joint Special Operations Command, a Logistic Support Command, and a Communic | E9: $215.338 billion (2023 est.) $211.35 billion (2022 est.) $203.146 billion (2021 est.) note: data in 2021 dollars | F9: urban population: 76.7% of total population (2023) rate of urbanization: -0.28% annual rate of change (2020-25 est.) | G9: electrification - total population: 100% (2022 est.) electrification - urban areas: 100% electrification - rural areas: 99.6% | H9: Europe
A10: Canada | B10: Northern North America, bordering the North Atlantic Ocean on the east, North Pacific Ocean on the west, and the Arctic Ocean on the north, north of the conterminous US | C10: high-income economy and second-largest US trading partner; key timber, oil, and gas industries; trade uncertainties and weak business investments contributing to economic slowdown; high and growing public debt; inflation moderating but remains above target range | D10: Canadian Forces: Canadian Army, Royal Canadian Navy, Royal Canadian Air Force (2025) note 1: the CAF is comprised of both a Regular Force and a Reserve Force; the Reserve Force is comprised of the Primary Reserve, Canadian Rangers, Cadet Organizations Administration and Training Service, and the Supplementary Reserve; the Canadian Rangers are part | E10: $2.242 trillion (2023 est.) $2.215 trillion (2022 est.) $2.133 trillion (2021 est.) note: data in 2021 dollars | F10: urban population: 81.9% of total population (2023) rate of urbanization: 0.95% annual rate of change (2020-25 est.) | G10: electrification - total population: 100% (2022 est.) | H10: North America
A11: Chile | B11: Southern South America, bordering the South Pacific Ocean, between Argentina and Peru | C11: export-driven economy; leading copper producer; though hit by COVID-19, fairly quick rebound from increased liquidity and rapid vaccine rollouts; decreasing poverty but still lingering inequality; public debt rising but still manageable; recent political violence has had negative economic consequences | D11: Armed Forces of Chile (<span class=\ | E11: $579.201 billion (2023 est.) $577.937 billion (2022 est.) $566.279 billion (2021 est.) note: data in 2021 dollars | F11: urban population: 88% of total population (2023) rate of urbanization: 0.78% annual rate of change (2020-25 est.) | G11: electrification - total population: 100% (2022 est.) | H11: South America
A12: China | B12: Eastern Asia, bordering the East China Sea, Korea Bay, Yellow Sea, and South China Sea, between North Korea and Vietnam | C12: world&rsquo;s second-largest economy by nominal GDP; global leader in exports and manufacturing; historically strong growth slowing; challenges of aging workforce, weak productivity, rising youth unemployment, struggling property sector, and public debt; state-sponsored economic controls and infrastructure investments | D12: People's Liberation Army (PLA): Ground Forces or People's Liberation Army Army (PLAA), Navy (PLAN, includes Marine Corps (PLANMC)), Air Force (PLAAF), Rocket Force (PLARF), Aerospace Force (ASF), Cyberspace Force (CSF), Information Support Force (ISF), Joint Logistics Support Force (JLSF), People's Armed Police (PAP, includes Coast Guard, Border De | E12: $31.23 trillion (2023 est.) $29.672 trillion (2022 est.) $28.822 trillion (2021 est.) note: data in 2021 dollars | F12: urban population: 64.6% of total population (2023) rate of urbanization: 1.78% annual rate of change (2020-25 est.) note: data do not include Hong Kong and Macau | G12: electrification - total population: 100% (2022 est.) | H12: East and Southeast Asia
A13: Colombia | B13: Northern South America, bordering the Caribbean Sea, between Panama and Venezuela, and bordering the North Pacific Ocean, between Ecuador and Panama | C13: prior to COVID-19, one of the most consistent growth economies; declining poverty; large stimulus package has mitigated economic fallout, but delayed key infrastructure investments; successful inflation management; sound flexible exchange rate regime; domestic economy suffers from lack of trade integration and infrastructure | D13: Military Forces of Colombia (Fuerzas Militares de Colombia<em lang=\ | E13: $978.007 billion (2023 est.) $972.073 billion (2022 est.) $906.034 billion (2021 est.) note: data in 2021 dollars | F13: urban population: 82.4% of total population (2023) rate of urbanization: 1.01% annual rate of change (2020-25 est.) | G13: electrification - total population: 100% (2022 est.) | H13: South America
A14: Costa Rica | B14: Central America, bordering both the Caribbean Sea and the North Pacific Ocean, between Nicaragua and Panama | C14: trade-based upper middle-income economy; green economy leader, having reversed deforestation; investing in blue economy infrastructure; declining poverty until hard impacts of COVID-19; lingering inequality and growing government debts have prompted a liquidity crisis | D14: Ministry of Public Security (Ministerio de Seguridad P&uacute;blica de Costa Rica): National Police (Fuerza P&uacute;blica), Air Surveillance Service (Servicio de Vigilancia A&eacute;rea), National Coast Guard Service (Servicio Nacional de Guardacostas), Drug Control Police (Polic&iacute;a Control de Drogas), Border Police (Policia de Fronteras), P | E14: $134.238 billion (2023 est.) $127.71 billion (2022 est.) $122.15 billion (2021 est.) note: data in 2021 dollars | F14: urban population: 82.6% of total population (2023) rate of urbanization: 1.5% annual rate of change (2020-25 est.) | G14: electrification - total population: 100% (2022 est.) | H14: Central America and the Caribbean
... A59: Sweden | B59: Northern Europe, bordering the Baltic Sea, Gulf of Bothnia, Kattegat, and Skagerrak, between Finland and Norway | C59: high-income, largest Nordic economy; EU member but does not use the euro; export-oriented, led by automotive, electronics, machinery, and pharmaceuticals; highly ranked for competitiveness, R&amp;D investments and governance; recovery, with falling inflation and real wage growth balanced by risks from trade uncertainty | D59: Swedish Armed Forces (Forsvarsmakten): Army, Navy, Air Force, Home Guard (202) | E59: $665.016 billion (2023 est.) $667.089 billion (2022 est.) $657.494 billion (2021 est.) note: data in 2021 dollars | F59: urban population: 88.7% of total population (2023) rate of urbanization: 0.89% annual rate of change (2020-25 est.) | G59: electrification - total population: 100% (2022 est.) | H59: Europe
A60: Taiwan | B60: Eastern Asia, islands bordering the East China Sea, Philippine Sea, South China Sea, and Taiwan Strait, north of the Philippines, off the southeastern coast of China | C60: high-income East Asian economy; most technologically advanced computer microchip manufacturing; increasing Chinese interference threatens market capabilities; minimum wages rising; longstanding regional socioeconomic inequality | D60: Taiwan Armed Forces: Army, Navy (includes Marine Corps), Air ForceOcean Affairs Council: Coast Guard Administration (CGA)Ministry of Interior: National Police (2025) note: the CGA is a law enforcement organization with homeland security functions during peacetime and national defense missions during wartime | E60: $1.743 trillion (2023 est.) $1.664 trillion (2022 est.) $1.512 trillion (2021 est.) | F60: urban population: 80.1% of total population (2023) rate of urbanization: 0.65% annual rate of change (2020-25 est.) | H60: East and Southeast Asia
A61: Thailand | B61: Southeastern Asia, bordering the Andaman Sea and the Gulf of Thailand, southeast of Burma | C61: upper middle-income Southeast Asian economy; substantial infrastructure; major electronics, food, and automobile parts exporter; globally used currency; extremely low unemployment, even amid COVID-19; ongoing Thailand 4.0 economic development | D61: Royal Thai Armed Forces (RTARF): Royal Thai Army (RTA), Royal Thai Navy (RTN; includes Royal Thai Marine Corps), Royal Thai Air Force (RTAF)Office of the Prime Minister: Royal Thai Police (2025) note: official paramilitary forces in Thailand include the Thai Rangers (Thahan Phran or \ | E61: $1.516 trillion (2023 est.) $1.488 trillion (2022 est.) $1.452 trillion (2021 est.) note: data in 2021 dollars | F61: urban population: 53.6% of total population (2023) rate of urbanization: 1.43% annual rate of change (2020-25 est.) | G61: electrification - total population: 99.9% (2022 est.) electrification - urban areas: 100% electrification - rural areas: 100% | H61: East and Southeast Asia
A62: Turkey | B62: Southeastern Europe and Southwestern Asia (that portion of Turkey west of the Bosporus is geographically part of Europe), bordering the Black Sea, between Bulgaria and Georgia, and bordering the Aegea | C62: upper-middle-income, diversified Middle Eastern economy; industrializing economy that maintains large agricultural base; key energy, tourism, and construction sectors; high inflation, interest rates, and foreign debt pose risk to financial stability | D62: Turkish Armed Forces (TAF; Turk Silahlı Kuvvetleri, TSK): Turkish Land Forces (Turk Kara Kuvvetleri), Turkish Naval Forces (Turk Deniz Kuvvetleri; includes naval air and naval infantry), Turkish Air Forces (Turk Hava Kuvvetleri)Ministry of Interior: Gendarmerie General Command (aka Gendarmerie of the Turkish Republic), Turkish Coast Guard Command, | E62: $2.953 trillion (2023 est.) $2.81 trillion (2022 est.) $2.662 trillion (2021 est.) note: data in 2021 dollars | F62: urban population: 77.5% of total population (2023) rate of urbanization: 1.11% annual rate of change (2020-25 est.) | G62: electrification - total population: 100% (2022 est.) | H62: Middle East
A63: Ukraine | B63: Eastern Europe, bordering the Black Sea, between Poland, Belarus, Romania, and Moldova in the west and Russia in the east | C63: lower-middle-income, non-EU, Eastern European economy; key wheat and corn exporter; gradual recovery after 30% GDP contraction at start of war; damage to infrastructure and agriculture balanced by consumer and business resilience in western Ukraine; international aid has stabilized foreign exchange reserves, allowing managed currency float; continu | D63: Armed Forces of Ukraine (AFU; Zbroyni Syly Ukrayiny or ZSU): Ground Forces, Naval Forces, Air Forces, Air Assault Forces, Marine Corps, Special Operations Forces, Unmanned Systems Forces, Territorial Defense Forces (Reserves)Ministry of Internal Affairs: National Guard of Ukraine, State Border Guard Service of Ukraine (includes Maritime Border Guar | E63: $560.111 billion (2023 est.) $531.796 billion (2022 est.) $746.471 billion (2021 est.) note: data in 2021 dollars | F63: urban population: 70.1% of total population (2023) rate of urbanization: -0.27% annual rate of change (2020-25 est.) | G63: electrification - total population: 100% (2022 est.) | H63: Europe
A64: United Arab Emirates | B64: Middle East, bordering the Gulf of Oman and the Persian Gulf, between Oman and Saudi Arabia | C64: high-income, oil-driven Middle Eastern economy; fastest GDP growth of Gulf states; diversification through tourism, construction, and services; strong foreign direct investment orientation; continued government investment and business-friendly reforms | D64: United Arab Emirates Armed Forces: Land Forces (Army), Navy, Air Force, Presidential Guard (includes special operations forces), National Guard (includes Coast Guard) (2025) note: each emirate maintains a local police force called a general directorate, which is officially a branch of the federal Ministry of Interior; all emirate-level general dire | E64: $718.95 billion (2023 est.) $693.842 billion (2022 est.) $645.376 billion (2021 est.) note: data in 2021 dollars | F64: urban population: 87.8% of total population (2023) rate of urbanization: 1.5% annual rate of change (2020-25 est.) | G64: electrification - total population: 100% (2022 est.) | H64: Middle East
A65: United Kingdom | B65: Western Europe, islands - including the northern one-sixth of the island of Ireland - between the North Atlantic Ocean and the North Sea; northwest of France | C65: high-income, non-EU European economy; global financial center and dominant service sector; sluggish growth from stringent monetary policy, reduced business investment, low productivity and participation rates; fiscal austerity in face of high public debt | D65: United Kingdom Armed Forces (aka British Armed Forces, aka His Majesty's Armed Forces): British Army, Royal Navy (includes Royal Marines), Royal Air Force (2025) | E65: $3.728 trillion (2023 est.) $3.715 trillion (2022 est.) $3.544 trillion (2021 est.) note: data in 2021 dollars | F65: urban population: 84.6% of total population (2023) rate of urbanization: 0.8% annual rate of change (2020-25 est.) | G65: electrification - total population: 100% (2022 est.) electrification - urban areas: 99.9% electrification - rural areas: 100% | H65: Europe
A66: United States | B66: North America, bordering both the North Atlantic Ocean and the North Pacific Ocean, between Canada and Mexico | C66: world&rsquo;s largest economy by nominal GDP; largest importer and second-largest exporter; home to leading financial exchanges and global reserve currency; high and growing public debt; inflation moderating but remains above pre-pandemic levels | D66: United States Armed Forces (aka US Military): US Army (USA), US Navy (USN; includes US Marine Corps or USMC), US Air Force (USAF), US Space Force (USSF); US Coast Guard (USCG); National Guard (Army National Guard and Air National Guard) (2025) note 1: the US Coast Guard is administered in peacetime by the Department of Homeland Security, but in war | E66: $24.977 trillion (2023 est.) $24.276 trillion (2022 est.) $23.681 trillion (2021 est.) note: data in 2021 dollars | F66: urban population: 83.3% of total population (2023) rate of urbanization: 0.96% annual rate of change (2020-25 est.) | G66: electrification - total population: 100% (2022 est.) | H66: North America
A67: Vietnam | B67: Southeastern Asia, bordering the Gulf of Thailand, Gulf of Tonkin, and South China Sea, as well as China, Laos, and Cambodia | C67: lower middle-income socialist East Asian economy; rapid economic growth since Đổi Mới reforms; strong investment and productivity growth; tourism and manufacturing hub; TPP signatory; declining poverty aside from ethnic minorities; systemic corruption | D67: People's Army of Vietnam (PAVN; aka Vietnam People's Army, VPA): Ground Forces (Army), Navy (includes naval infantry), Air Defense - Air Force, Vietnam Border Guard, Vietnam Coast GuardVietnam People's Ministry of Public Security; Vietnam Civil Defense Force (2025) note 1: the People's Public Security Ministry is responsible for internal security a | E67: $1.354 trillion (2023 est.) $1.289 trillion (2022 est.) $1.192 trillion (2021 est.) note: data in 2021 dollars | F67: urban population: 39.5% of total population (2023) rate of urbanization: 2.7% annual rate of change (2020-25 est.) | G67: electrification - total population: 100% (2022 est.) | H67: East and Southeast Asia
A68: Yemen | B68: Middle East, bordering the Arabian Sea, Gulf of Aden, and Red Sea, between Oman and Saudi Arabia | C68: low-income Middle Eastern economy; infrastructure, trade, and economic institutions devastated by civil war; oil/gas-dependent but decreasing reserves; massive poverty, food insecurity, and unemployment; high inflation | D68: Yemeni Armed Forces: Yemeni National Army, Air Force and Air Defense, Navy and Coastal Defense Forces, Border Guard, Strategic Reserve Forces (includes Special Forces and Presidential Protection Brigades, which are under the Ministry of Defense but responsible to the president), Popular Committee Forces (aka Popular Resistance Forces; government-ba | E68: $73.63 billion (2017 est.) $78.28 billion (2016 est.) $90.63 billion (2015 est.) note: data are in 2017 dollars | F68: urban population: 39.8% of total population (2023) rate of urbanization: 3.71% annual rate of change (2015-20 est.) | G68: electrification - total population: 76% (2022 est.) electrification - urban areas: 96.1% electrification - rural areas: 65% | H68: Middle East

Sheet DATA_ACLED
A1: DATA_ACLED | Aggregated Per Country · 2023-2025
A2: Source: acleddata.com via live fetch 2026-07-04 | Rolling year window ending Jul 2026
A3: Country | B3: PV Events 2024–2026 | C3: PV Events 2026 | D3: Fatalities 2024–2026 | E3: Fatalities 2026 | F3: Civilian Events 2024–2026 | G3: Annual PV Rate
A4: Algeria | B4: 96 | C4: 19 | D4: 53 | E4: 18 | F4: 8 | G4: 96
A5: Argentina | B5: 1819 | C5: 531 | D5: 9 | E5: 0 | F5: 2 | G5: 1819
A6: Australia | B6: 723 | C6: 98 | D6: 16 | E6: 0 | F6: 0 | G6: 723
A7: Bahamas | B7: 11 | C7: 0 | D7: 0 | E7: 0 | F7: 1 | G7: 11
A8: Bahrain | B8: 945 | C8: 388 | D8: 3 | E8: 3 | F8: 11 | G8: 945
A9: Bulgaria | B9: 797 | C9: 96 | D9: 0 | E9: 0 | F9: 1 | G9: 797
A10: Canada | B10: 1472 | C10: 314 | D10: 7 | E10: 0 | F10: 2 | G10: 1472
A11: Chile | B11: 1281 | C11: 279 | D11: 12 | E11: 5 | F11: 47 | G11: 1281
A12: China | B12: 1576 | C12: 302 | D12: 2 | E12: 0 | F12: 165 | G12: 1576
A13: Colombia | B13: 5681 | C13: 1224 | D13: 2193 | E13: 416 | F13: 1235 | G13: 5681
A14: Costa Rica | B14: 127 | C14: 39 | D14: 2 | E14: 0 | F14: 9 | G14: 127
A15: Cuba | B15: 323 | C15: 172 | D15: 14 | E15: 0 | F15: 38 | G15: 323
... A68: Yemen | B68: 10760 | C68: 1424 | D68: 2022 | E68: 352 | F68: 857 | G68: 10760

Sheet DATA_PORTWATCH
A1: DATA_PORTWATCH | IMF PortWatch Chokepoint Database | Vessel Counts by Type
A2: Source: portwatch.imf.org · Based on satellite AIS signals · Download updated CSV weekly from portwatch.imf.org/datasets/
A3: Chokepoint | B3: Total Vessels | C3: Tankers | D3: Container | E3: Dry Bulk | F3: Top Industry 1 | G3: Top Industry 2
A4: Suez Canal | B4: 19787 | C4: 6418 | D4: 5513 | E4: 5222 | F4: Mineral Products | G4: Vegetable Products
A5: Panama Canal | B5: 11020 | C5: 4507 | D5: 2712 | E5: 2412 | F5: Mineral Products | G5: Vegetable Products
A6: Bosphorus / Turkish Straits | B6: 35125 | C6: 8555 | D6: 3015 | E6: 8058 | F6: Mineral Products | G6: Vegetable Products
A7: Bab el-Mandeb | B7: 19306 | C7: 6424 | D7: 5062 | E7: 5228 | F7: Mineral Products | G7: Chemical & Allied Industries
A8: Strait of Malacca | B8: 71451 | C8: 27469 | D8: 18154 | E8: 18336 | F8: Mineral Products | G8: Chemical & Allied Industries
A9: Strait of Hormuz | B9: 32496 | C9: 19540 | D9: 5274 | E9: 5414 | F9: Mineral Products | G9: Chemical & Allied Industries
A10: Cape of Good Hope | B10: 21531 | C10: 4706 | D10: 3493 | E10: 11736 | F10: Mineral Products | G10: Vegetable Products
A11: Strait of Gibraltar | B11: 47801 | C11: 15666 | D11: 11698 | E11: 10466 | F11: Mineral Products | G11: Vegetable Products
A12: Danish Straits | B12: 17833 | C12: 4318 | D12: 2135 | E12: 2248 | F12: Mineral Products | G12: Wood & Wood Products
A13: Taiwan Strait | B13: 88436 | C13: 20406 | D13: 31190 | E13: 23626 | F13: Mineral Products | G13: Vegetable Products
A14: Korea Strait | B14: 82119 | C14: 22732 | D14: 20682 | E14: 15163 | F14: Mineral Products | G14: Vegetable Products
A15: Lombok Strait | B15: 12918 | C15: 2616 | D15: 70 | E15: 9566 | F15: Mineral Products | G15: Vegetable Products
... A18: Strait of Magellan | B18: 1426 | C18: 359 | D18: 110 | E18: 790 | F18: Mineral Products | G18: Vegetable Products

Sheet DATA_FSI
A1: DATA_FSI | Fragile States Index 2023
A2: Source: Fund for Peace. Higher scores = more fragile state. Range 0-120.
A3: Country | B3: Rank | C3: TOTAL | D3: Demographic | E3: Refugees/IDPs | F3: Group Griev. | G3: Brain Drain | H3: Econ Ineq. | I3: Economy | J3: State Legit. | K3: Public Services | L3: Human Rights
A4: Somalia | B4: 1st | C4: 111.9 | D4: 10 | E4: 9 | F4: 8.7 | G4: 8.6 | H4: 9.1 | I4: 9.5 | J4: 9.6 | K4: 9.8
A5: Yemen | B5: 2nd | C5: 108.9 | D5: 9.6 | E5: 9.6 | F5: 8.8 | G5: 6.4 | H5: 7.9 | I5: 9.9 | J5: 9.8 | K5: 9.6
A6: Haiti | B6: 10th | C6: 102.9 | D6: 8.8 | E6: 7.7 | F6: 5.5 | G6: 8.3 | H6: 9.2 | I6: 8.9 | J6: 9.9 | K6: 9.8
A7: Ethiopia | B7: 11th | C7: 100.4 | D7: 9.8 | E7: 9.5 | F7: 8.9 | G7: 6.2 | H7: 7.5 | I7: 6.8 | J7: 8.2 | K7: 8.7
A8: Libya | B8: 17th | C8: 96.1 | D8: 6 | E8: 7.5 | F8: 7.3 | G8: 5 | H8: 6.4 | I8: 8.9 | J8: 9.6 | K8: 8
A9: Ukraine | B9: 18th | C9: 95.9 | D9: 7.3 | E9: 10 | F9: 6.8 | G9: 8.9 | H9: 4.9 | I9: 8.5 | J9: 6.4 | K9: 7.3
A10: Eritrea | B10: 19th | C10: 94.5 | D10: 7.7 | E10: 6.6 | F10: 8.7 | G10: 8.6 | H10: 7.9 | I10: 7.1 | J10: 9.7 | K10: 8.1
A11: Mozambique | B11: 22nd | C11: 94 | D11: 9.6 | E11: 7.9 | F11: 7.4 | G11: 7.1 | H11: 9.2 | I11: 7.7 | J11: 7.1 | K11: 9.7
A12: Iraq | B12: 27th | C12: 91.4 | D12: 8.2 | E12: 7.7 | F12: 8 | G12: 6.1 | H12: 5.7 | I12: 6.3 | J12: 8.3 | K12: 8.3
A13: North Korea | B13: 38th | C13: 87 | D13: 7.3 | E13: 3.2 | F13: 4.6 | G13: 3.2 | H13: 7.3 | I13: 8.7 | J13: 9.8 | K13: 8
A14: Iran | B14: 40th | C14: 85.4 | D14: 6.8 | E14: 5.5 | F14: 9.6 | G14: 4.9 | H14: 4.5 | I14: 7.6 | J14: 9.8 | K14: 4.1
A15: Djibouti | B15: 46th | C15: 82.2 | D15: 7.1 | E15: 7.1 | F15: 5.3 | G15: 4 | H15: 7.2 | I15: 7 | J15: 8.8 | K15: 7.6
... A67: Norway | B67: 179th | C67: 14.5 | D67: 1.4 | E67: 1.7 | F67: 3.1 | G67: 0.7 | H67: 1.4 | I67: 1.4 | J67: 0.4 | K67: 1

Sheet 00_CONFIG
A1: 00 CONFIGURATION | Ring & Pillar Weights | Risk Bands
A3: RING WEIGHTS (must sum to 1.00)
A4: Parameter | B4: Named Cell | C4: Weight | D4: Description
A5: Ring 1: Primary Controller(s) | B5: W_Ring1 | C5: 0.5 | D5: Countries that physically control the chokepoint
A6: Ring 2: Surrounding Countries | B6: W_Ring2 | C6: 0.25 | D6: Adjacent states with operational influence
A7: Ring 3: Outside Influencers | B7: W_Ring3 | C7: 0.15 | D7: Great powers / regional actors shaping Rings 1+2
A8: Ring 4: Environmental Modifier | B8: W_Ring4 | C8: 0.1 | D8: ERA5 weather · geography · bypass availability
B9: SUM → | C9: =SUM(C5:C8) -> 1
A11: COUNTRY-RISK PILLAR WEIGHTS (must sum to 1.00)
A12: Pillar | B12: Named Cell | C12: Weight | D12: Description
A13: P1: Governance & Corruption | B13: W_P1 | C13: 0.2 | D13: CPI · Democracy · Rule of Law · Freedom Index
A14: P2: Economic Strength | B14: W_P2 | C14: 0.15 | D14: GDP/cap (log) · Inflation · Unemployment · Debt/GDP
A15: P3: Security Environment | B15: W_P3 | C15: 0.2 | D15: GPI · Terrorism Index · Military Spend · ACLED events
A16: P4: Political Stability | B16: W_P4 | C16: 0.15 | D16: Political Stability Percentile · FSI Total
A17: P5: External Influence | B17: W_P5 | C17: 0.15 | D17: Proxy: Military spend + conflict pressure (pending sanctions data)
A18: P6: Infrastructure | B18: W_P6 | C18: 0.15 | D18: Electricity access % · GDP/cap (log)
B19: SUM → | C19: =SUM(C13:C18) -> 1
A21: RISK BANDS
A22: Score Range | B22: Band | C22: Hex | D22: Action
A23: 0 – 20 | B23: LOW | C23: #27AE60 | D23: Proceed. Standard monitoring.
A24: 21 – 40 | B24: MODERATE | C24: #F1C40F | D24: Enhanced monitoring. Quarterly review.
A25: 41 – 60 | B25: ELEVATED | C25: #E67E22 | D25: Flag for review. Identify bypass routes.
A26: 61 – 80 | B26: HIGH | C26: #E74C3C | D26: Escalate. Reroute planning required.
A27: 81 – 100 | B27: CRITICAL | C27: #C0392B | D27: Immediate escalation. Do not rely on route.

Sheet METHODOLOGY
A1: SCORING METHODOLOGY
B3: STEP 1 WINSORIZATION
B4: Extreme values (top/bottom 2.5% of each indicator's distribution) are CAPPED at the 2.5th and 97.5th percentiles. This prevents outliers like Yemen's inflation or Singapore's GDP/capita from dominating the entire distribution and pulling normal countries toward the middle. So, standard practice in enterprise credit and country risk scorin is followoed using Moody's, S&P, MSCI the models for those varients.
B6: STEP 2 MIN-MAX NORMALIZATION
B7: Every raw indicator is rescaled to a 0-100 scale using min-max normalization across the population of 65 target countries. The formula is: normalized = (value - min) / (max - min) × 100. This makes indicators on wildly different native scales (GDP in USD vs Terrorism Index 0-10 vs Debt as % of GDP) to be better cross referenced and averageable.
B9: STEP 3 DIRECTION HANDLING
B10: Indicators where HIGHER = BETTER (CPI, Democracy Index, Rule of Law, Freedom Index, GDP/capita, Political Stability, Electricity Access) are INVERTED so that HIGHER = HIGHER RISK on the 0-100 scale. This ensures every score reads the same direction and can be averaged without silent bias.
B12: STEP 4 LOG TRANSFORMATION
B13: GDP per capita is log transformed BEFORE normalization because the distribution is heavily right-skewed (Luxembourg $158k vs Somalia $500). Without log transform, min-max would compress everyone except the top 3 into the bottom 10% of the scale (not good).
B15: STEP 5 PILLAR AGGREGATION
B16: Within each of the six pillars, the normalized indicators are scored as the average with EQUAL WEIGHT. Missing indicators are dropped from the average rather than assumed, so a country with 3 out of 4 governance indicators can still get a valid score based on what's available.
B18: STEP 6 COUNTRY RISK
B19: The Country Risk Score is weighted as the average of the six pillars using the weights in 00_CONFIG. If you change the weights in the Config sheet, the whole model will recalculate (just remember to save). Currently at P1=20%, P2=15%, P3=20%, P4=15%, P5=15%, P6=15%.
... B31: If a cell is empty, the index did not publish a score for that country. So, the model still scored that country using everything else it had.
